Workbook

Sheet README
A1: Item | B1: Value
A2: Issuer | B2: Fastned B.V.
A3: Data as of | B3: H1-2026
A4: Written | B4: 2026-10-24
A5: Units | B5: EUR m unless stated; days and headcount as counts; ratios as decimals
A6: Signs | B6: profits positive, losses negative; net interest = net finance cost, positive; capex and D&A positive
A7: Periods | B7: FY2025 = fiscal year ending in 2025; H1-2026 = half-year to 30 June 2026; FY2026E = a year after the last one reported: the company's budget or plan for it, or an amount falling due then. One column per year: debt falling due in a year since reported sits in that year (as the report before states it), a plan figure for such a year in its budget row; a band of years (FY2027E-FY2029E) stays in Facts
A8: Record | B8: one value per field and period: approved before pending, audited before unaudited, the later report wins where restated (mvp/screen.py)
A9: Status | B9: ok = approved by a named reviewer; rep = management representation, attested by a named officer; pend = extracted, pending review; rej = rejected; grey cell = pending, gold cell = management representation
A10: Sources | B10: every number links to its row in Facts; the row links to the page of the published PDF or to the web source
A11: Formulas | B11: Ratios are live Excel formulas on the Financials cells, the same formulas as the platform; one-off income = the items in Bridge
A12: Scope | B12: facts and arithmetic on printed formulas only: no rating, no score, no recommendation. Demo built from the company's public reports.

Sheet Financials
A1: EUR m unless stated | B1: FY2019 | C1: FY2020 | D1: FY2021 | E1: FY2022 | F1: FY2023 | G1: FY2024 | H1: FY2025 | I1: H1-2024 | J1: H1-2025 | K1: H1-2026 | L1: FY2026E | M1: FY2027E
A2: Identity
A3: Employees (FTE, period end) | E3: 146 | F3: 172 | G3: 265 | H3: 414 | J3: 354 | K3: 432
A4: Historical financials and quality of earnings
A5: Revenue | B5: 4.5 | C5: 6.3 | D5: 12.4 | E5: 36 | F5: 60.5 | G5: 83.8 | H5: 139.2 | I5: 37.8 | J5: 57.8 | K5: 83.5
A6: EBITDA (as reported) | D6: -12.6 | E6: -4.6 | F6: 4.6 | G6: 7.4 | H6: 14.8 | I6: 3.3 | J6: 3 | K6: 15.9
A7: EBITDA adjusted / underlying (as reported) | D7: -4.4 | E7: -4 | F7: 7.8 | G7: 8.7 | H7: 8.3 | I7: 3.2 | J7: 1.4 | K7: 13.7
A8: EBIT / operating result | E8: -14.4 | F8: -12.1 | G8: -16.1 | H8: -13.6 | J8: -10 | K8: -1.7
A9: Net result | D9: -24.6 | E9: -22.2 | F9: -19.3 | G9: -26.6 | H9: -30.2 | I9: -11.4 | J9: -18.3 | K9: -13
A10: Depreciation & amortisation | D10: 5.9 | E10: 10.3 | F10: 16.7 | G10: 23.4 | H10: 28.4 | I10: 9.8 | J10: 13 | K10: 17.6
A11: Net finance cost | D11: 6.2 | E11: 7.4 | F11: 6.8 | G11: 10.9 | H11: 16.4 | I11: 4.9 | J11: 8.2 | K11: 11.2
A12: Cash flow from operating activities | D12: -10 | E12: -10.8 | F12: -3.1 | G12: -7.6 | H12: -20.4 | J12: -6 | K12: -10.1
A13: Capex (PP&E + intangibles) | D13: 36.6 | E13: 67.5 | F13: 66.8 | G13: 68 | H13: 81.7 | J13: 41 | K13: 44.7
A14: Cash & equivalents | D14: 128.6 | E14: 149.5 | F14: 126.6 | G14: 117.4 | H14: 69.9 | J14: 112.7 | K14: 100.7
A15: Gross financial debt (bonds + loans, excl. leases) | E15: 112.9 | F15: 161 | G15: 226.5 | H15: 295.1 | K15: 379.5
A16: Lease liabilities | E16: 9.8 | F16: 21.2 | G16: 37.7 | H16: 62.9 | K16: 76.9
A17: Net debt (as reported) | G17: 146.8 | H17: 288
A18: Total equity | D18: 109.2 | E18: 160.6 | F18: 146.2 | G18: 122.7 | H18: 91.9 | J18: 104.1 | K18: 80.8
A19: Total assets | D19: 214.6 | E19: 315.2 | F19: 357.5 | G19: 426.7 | H19: 501.8 | K19: 595.3
A20: Days from year end to filing of the accounts | F20: 87 | G20: 85 | H20: 78 | K20: 37
A21: Income taxes paid (cash flow statement) | E21: 0 | F21: 0 | G21: 0 | H21: 0 | J21: 0 | K21: 0
A22: Transaction, plan, projections and downside
A23: Order book / contracted revenue (period end) | H23: 23.9
A24: Debt principal falling due in the period | F24: 8.9 | G24: 17 | H24: 21.9 | L24: 12.4 | M24: 7.3

Sheet Bridge
A1: Period | B1: One-off income inside EBITDA, as itemised in the reports | C1: EUR m counted | D1: Fact | E1: Rule

Sheet Ratios
A1: Live formulas on Financials | B1: FY2019 | C1: FY2020 | D1: FY2021 | E1: FY2022 | F1: FY2023 | G1: FY2024 | H1: FY2025 | I1: H1-2024 | J1: H1-2025 | K1: H1-2026 | L1: Formula
A2: One-off income inside EBITDA | B2: =SUMIF(Bridge!$A:$A,"FY2019",Bridge!$C:$C) | C2: =SUMIF(Bridge!$A:$A,"FY2020",Bridge!$C:$C) | D2: =SUMIF(Bridge!$A:$A,"FY2021",Bridge!$C:$C) | E2: =SUMIF(Bridge!$A:$A,"FY2022",Bridge!$C:$C) | F2: =SUMIF(Bridge!$A:$A,"FY2023",Bridge!$C:$C) | G2: =SUMIF(Bridge!$A:$A,"FY2024",Bridge!$C:$C) | H2: =SUMIF(Bridge!$A:$A,"FY2025",Bridge!$C:$C) | I2: =SUMIF(Bridge!$A:$A,"H1-2024",Bridge!$C:$C) | J2: =SUMIF(Bridge!$A:$A,"H1-2025",Bridge!$C:$C) | K2: =SUMIF(Bridge!$A:$A,"H1-2026",Bridge!$C:$C) | L2: SUM of Bridge for the period
A3: EBITDA excluding one-off income | D3: =(Financials!D6-SUMIF(Bridge!$A:$A,"FY2021",Bridge!$C:$C)) | E3: =(Financials!E6-SUMIF(Bridge!$A:$A,"FY2022",Bridge!$C:$C)) | F3: =(Financials!F6-SUMIF(Bridge!$A:$A,"FY2023",Bridge!$C:$C)) | G3: =(Financials!G6-SUMIF(Bridge!$A:$A,"FY2024",Bridge!$C:$C)) | H3: =(Financials!H6-SUMIF(Bridge!$A:$A,"FY2025",Bridge!$C:$C)) | I3: =(Financials!I6-SUMIF(Bridge!$A:$A,"H1-2024",Bridge!$C:$C)) | J3: =(Financials!J6-SUMIF(Bridge!$A:$A,"H1-2025",Bridge!$C:$C)) | K3: =(Financials!K6-SUMIF(Bridge!$A:$A,"H1-2026",Bridge!$C:$C)) | L3: EBITDA as reported − one-off income
A4: EBITDA margin excluding one-off income | D4: =IFERROR((Financials!D6-SUMIF(Bridge!$A:$A,"FY2021",Bridge!$C:$C))/Financials!D5,"") | E4: =IFERROR((Financials!E6-SUMIF(Bridge!$A:$A,"FY2022",Bridge!$C:$C))/Financials!E5,"") | F4: =IFERROR((Financials!F6-SUMIF(Bridge!$A:$A,"FY2023",Bridge!$C:$C))/Financials!F5,"") | G4: =IFERROR((Financials!G6-SUMIF(Bridge!$A:$A,"FY2024",Bridge!$C:$C))/Financials!G5,"") | H4: =IFERROR((Financials!H6-SUMIF(Bridge!$A:$A,"FY2025",Bridge!$C:$C))/Financials!H5,"") | I4: =IFERROR((Financials!I6-SUMIF(Bridge!$A:$A,"H1-2024",Bridge!$C:$C))/Financials!I5,"") | J4: =IFERROR((Financials!J6-SUMIF(Bridge!$A:$A,"H1-2025",Bridge!$C:$C))/Financials!J5,"") | K4: =IFERROR((Financials!K6-SUMIF(Bridge!$A:$A,"H1-2026",Bridge!$C:$C))/Financials!K5,"") | L4: EBITDA excluding one-off income / revenue
A5: Free cash flow | D5: =IFERROR(Financials!D12-Financials!D13,"") | E5: =IFERROR(Financials!E12-Financials!E13,"") | F5: =IFERROR(Financials!F12-Financials!F13,"") | G5: =IFERROR(Financials!G12-Financials!G13,"") | H5: =IFERROR(Financials!H12-Financials!H13,"") | J5: =IFERROR(Financials!J12-Financials!J13,"") | K5: =IFERROR(Financials!K12-Financials!K13,"") | L5: operating cash flow − capex
A6: Gross debt excluding leases, calculated | L6: net debt as reported + cash − lease liabilities, where the report states no total (as mvp/schema.py derive)
A7: Net debt excluding leases | E7: =(Financials!E15-Financials!E14) | F7: =(Financials!F15-Financials!F14) | G7: =(Financials!G15-Financials!G14) | H7: =(Financials!H15-Financials!H14) | K7: =(Financials!K15-Financials!K14) | L7: gross debt excluding leases − cash
A8: Net debt / EBITDA excluding one-off income | E8: =IFERROR((Financials!E15-Financials!E14)/(Financials!E6-SUMIF(Bridge!$A:$A,"FY2022",Bridge!$C:$C)),"") | F8: =IFERROR((Financials!F15-Financials!F14)/(Financials!F6-SUMIF(Bridge!$A:$A,"FY2023",Bridge!$C:$C)),"") | G8: =IFERROR((Financials!G15-Financials!G14)/(Financials!G6-SUMIF(Bridge!$A:$A,"FY2024",Bridge!$C:$C)),"") | H8: =IFERROR((Financials!H15-Financials!H14)/(Financials!H6-SUMIF(Bridge!$A:$A,"FY2025",Bridge!$C:$C)),"") | L8: net debt excluding leases / EBITDA excluding one-off income; fiscal years
A9: EBITDA excluding one-off income / net interest | D9: =IFERROR((Financials!D6-SUMIF(Bridge!$A:$A,"FY2021",Bridge!$C:$C))/Financials!D11,"") | E9: =IFERROR((Financials!E6-SUMIF(Bridge!$A:$A,"FY2022",Bridge!$C:$C))/Financials!E11,"") | F9: =IFERROR((Financials!F6-SUMIF(Bridge!$A:$A,"FY2023",Bridge!$C:$C))/Financials!F11,"") | G9: =IFERROR((Financials!G6-SUMIF(Bridge!$A:$A,"FY2024",Bridge!$C:$C))/Financials!G11,"") | H9: =IFERROR((Financials!H6-SUMIF(Bridge!$A:$A,"FY2025",Bridge!$C:$C))/Financials!H11,"") | L9: EBITDA excluding one-off income / net finance cost; fiscal years
A10: Equity ratio | D10: =IFERROR(Financials!D18/Financials!D19,"") | E10: =IFERROR(Financials!E18/Financials!E19,"") | F10: =IFERROR(Financials!F18/Financials!F19,"") | G10: =IFERROR(Financials!G18/Financials!G19,"") | H10: =IFERROR(Financials!H18/Financials!H19,"") | K10: =IFERROR(Financials!K18/Financials!K19,"") | L10: equity / total assets

Sheet Maturities
A1: Falls due | B1: Principal | C1: Leases | D1: Interest | E1: Facts | F1: Note
A2: 2026 | B2: 10.7 | E2: F1856, F1858 | F2: Unsecured retail bonds 5.0%, due 12 Dec 2026: 10.3; 4% secured loan (Caisse des Depots), current instalment due 1 Dec 2026: 0.4
A3: 2027 | B3: 5.2 | E3: F1857 | F3: Unsecured retail bonds 5.0%, due 21 Jun 2027: 5.2
A4: 2028 | B4: 58.9 | E4: F1859, F1860 | F4: Unsecured retail bonds 5.5%, due 12 Jun 2028: 24.4; Unsecured retail bonds 6.0%, due 16 Oct 2028: 34.5
A5: 2029 | B5: 83.1 | E5: F1861, F1862, F1863 | F5: Unsecured retail bonds 6.0%, due 19 Feb 2029: 27.9; Unsecured retail bonds 6.0%, due 21 Jun 2029: 33.1; Unsecured retail bonds 6.0%, due 30 Oct 2029: 22.1
A6: 2030 | B6: 110.4 | E6: F1864, F1865, F1866 | F6: Unsecured retail bonds 6.0%, due 19 Feb 2030: 36.5; Unsecured retail bonds 6.0%, due 21 Jun 2030: 34.8; Unsecured retail bonds 6.0%, due 30 Oct 2030: 39.1
A7: 2031 | B7: 89.5 | E7: F1867, F1868, F1869, F1872, F1873, F1874 | F7: Unsecured retail bonds 6.0%, due 10 Mar 2031: 32.4; Unsecured retail bonds 6.0%, due 21 Jun 2031: 36.5; 4% secured loan (Caisse des Depots), due 1 Dec 2031: 1.7; Green loan Facility A1 (EUR 55m commitment), floating EURIBOR + margin, matures 22 Jan…: 13.4; Green loan Facility A2 (CHF 23.2m commitment), floating SARON + margin, matures 22 Jan…: 1.7; Green loan Facility B (EUR 20m commitment), fixed rate, matures 22 Jan 2031, senior…: 3.8
A8: 2032 | B8: 21.6 | E8: F1870, F1871 | F8: 4% secured loan (Caisse des Depots), due 1 Dec 2032: 12.6; German Regional Tender government grant treated as interest-free loan (financial…: 9.0
A9: leases, not dated by year | C9: 76.9 | E9: F1849 | F9: lease liabilities at H1-2026
F10: principal per year of maturity, the carrying amounts of the instrument table in the H1-2026 report (S4 p43); leases are not dated by year there
F11: the 19 lines add up to 379.4, gross debt excluding leases at H1-2026 is 379.5

Sheet Debt
A1: Period | B1: Item | C1: Source | D1: Page | E1: Fact
B2: INSTRUMENTS
B3: Unsecured retail bonds 5.0%, due 12 Dec 2026, carrying EUR 10.3m (31 Dec 2025: 12.0), unsecured, not subordinated, unlisted | C3: S4 | D3: 43 | E3: F1856
B4: Unsecured retail bonds 5.0%, due 21 Jun 2027, EUR 5.2m (31 Dec 2025: 7.3) | C4: S4 | D4: 43 | E4: F1857
B5: 4% secured loan (Caisse des Depots), current instalment due 1 Dec 2026, EUR 0.4m | C5: S4 | D5: 43 | E5: F1858
B6: Unsecured retail bonds 5.5%, due 12 Jun 2028, EUR 24.4m | C6: S4 | D6: 43 | E6: F1859
B7: Unsecured retail bonds 6.0%, due 16 Oct 2028, EUR 34.5m | C7: S4 | D7: 43 | E7: F1860
B8: Unsecured retail bonds 6.0%, due 19 Feb 2029, EUR 27.9m | C8: S4 | D8: 43 | E8: F1861
B9: Unsecured retail bonds 6.0%, due 21 Jun 2029, EUR 33.1m | C9: S4 | D9: 43 | E9: F1862
B10: Unsecured retail bonds 6.0%, due 30 Oct 2029, EUR 22.1m | C10: S4 | D10: 43 | E10: F1863
B11: Unsecured retail bonds 6.0%, due 19 Feb 2030, EUR 36.5m | C11: S4 | D11: 43 | E11: F1864
B12: Unsecured retail bonds 6.0%, due 21 Jun 2030, EUR 34.8m | C12: S4 | D12: 43 | E12: F1865
B13: Unsecured retail bonds 6.0%, due 30 Oct 2030, EUR 39.1m | C13: S4 | D13: 43 | E13: F1866
B14: Unsecured retail bonds 6.0%, due 10 Mar 2031, EUR 32.4m, issued Feb-Mar 2026 (30.1 new money, 2.3 extended) | C14: S4 | D14: 43 | E14: F1867
... B63: 4% secured loan from Caisse des Dépôts maturing 01/12/2032, EUR 1,921k drawn in 2023 | C63: S1 | D63: 136 | E63: F166
B64: COVENANTS AND TERMS
B65: covenant: minimum tangible equity and minimum tangible equity to total assets (bank guarantee facility, Fastned B.V. company level); formula as defined: tangible equity; tangible equity divided by total assets; threshold: not disclosed; direction: min; test frequency: quarterly | C65: S3 | D65: 184 | E65: F1686
B66: Retail bonds: no security and no covenants that could require Fastned to repay. | C66: S4 | D66: 44 | E66: F1876
B67: Green loan facility: secured, senior, subject to financial covenants first tested on 31 December 2029. | C67: S4 | D67: 44 | E67: F1877
B68: Bank guarantee facility (EUR 20m): all financial covenants removed in H1 2026; uncommitted and unsecured. | C68: S4 | D68: 48 | E68: F1878
B69: The unsecured bonds carry no financial covenants that could require Fastned to repay the loans and no security. | C69: S3 | D69: 173 | E69: F1221
B70: Bank guarantee facility covenants: Fastned B.V. as borrower must maintain a minimum level of tangible equity and a minimum ratio of tangible equity to total assets; tested quarterly by management; complied at 31 Dec 2025. | C70: S3 | D70: 184 | E70: F1222
B71: TICO Financing contains financial covenants including leverage and interest cover tests and restrictions on additional indebtedness and distributions; thresholds not disclosed. | C71: S3 | D71: 195 | E71: F1223
B72: Bonds carry no security and no covenants that could require Fastned to repay any of the loans. | C72: S2 | D72: 147 | E72: F634
B73: No covenants apply to the bonds that could require early repayment; bonds are unsecured. | C73: S1 | D73: 136 | E73: F167
B74: term: holders (retail bonds); value: thousands of retail investors in the Netherlands and Belgium, more than 12,000 bondholders | C74: S4 | D74: 12 | E74: F2041
B75: term: rate type (retail bonds 2026 series); value: fixed 6% per annum, payable quarterly in arrears | C75: S4 | D75: 44 | E75: F2042
B76: term: call; value: Group may repay all or part of outstanding bonds at any time where the Final Terms of the series allow early redemption | C76: S4 | D76: 44 | E76: F2043
... B106: term: holders; value: retail investors (retail bond transactions, marketing for new bond issuances) | C106: S1 | D106: 199 | E106: F471

Sheet Guidance
A1: Year | B1: Metric | C1: Guidance as stated | D1: Reported | E1: Facts

Sheet Management
A1: Topic | B1: Fact | C1: Fact id
A2: person: Victor van Dijk | B2: VP Strategy, appointed March 2026. | C2: F1893
A3: person: Michiel Langezaal | B3: Co-founder and CEO, Management Board; President of ChargeUp Europe. | C3: F1894
A4: person: Francoise Poggi | B4: Chief Operating Officer, Management Board. | C4: F1895
A5: person: Remco Samuels | B5: CFO a.i. since March 2026 (not a Management Board signatory of the interim statements). | C5: F1896
A6: person: Patricia Allam | B6: Head of Funding and Investor Relations. | C6: F1897
A7: person: Matt Ersin | B7: Director of Government and Public Affairs; elected first Chair of the Green Industrial Grids Association (GIGA) in 2025. | C7: F1263
A8: person: Martijn Repko | B8: Country Director Netherlands (as of the 2025 annual report). | C8: F1264
A9: person: Pierre Courgeon | B9: Country Director France (as of the 2025 annual report). | C9: F1265
A10: owners | B10: Wilhelmina-Dok B.V. (Bart Lubbers) holds 36.7% of outstanding certificates of shares at end 2025 (2024: 36.7%). | C10: F1508
A11: owners | B11: Carraig Aonair Holding B.V. (Michiel Langezaal) holds 21.3% of outstanding certificates of shares at end 2025 (2024: 21.3%). | C11: F1509
A12: owners | B12: Breesaap B.V. holds 5.8% of the shares in Fastned B.V.; Bart Lubbers has a 33% share in Breesaap B.V. | C12: F1510
... A90: board | B90: name: Victor van Dijk; body: management; role: CFO | C90: F297

Sheet Risks
A1: Period | B1: Risk as the company states it | C1: Source | D1: Page | E1: Fact
B2: Operating cash flow H1 2026 includes EUR -6.3m timing of payments from the German highway authority and EUR -5.3m higher inventory from the delayed Q1 e-credit sale. | C2: S4 | D2: 19 | E2: F1879
B3: Management reports no material change to the risk profile presented in the 2025 Annual Report (pages 74-84). | C3: S4 | D3: 23 | E3: F1880
B4: Area of attention: dependence on key material suppliers and third parties; geopolitical developments and critical-material availability named as supply-chain risks. | C4: S4 | D4: 23 | E4: F1881
B5: Area of attention: grid capacity constraints and permit delays affect timing of station development in an increasing number of markets; timing largely outside Fastned's control. | C5: S4 | D5: 23 | E5: F1882
B6: Area of attention: external fraud (fraudulent charge-card use, invoice fraud), exposure expected to increase with new products. | C6: S4 | D6: 23 | E6: F1883
B7: Area of attention: health and safety in construction, maintenance and operation of stations. | C7: S4 | D7: 23 | E7: F1884
B8: Area of attention: scalable risk-management and internal-control framework; company plans to strengthen the framework after H1 2026 audits. | C8: S4 | D8: 23 | E8: F1885
B9: Current interest-bearing loans and borrowings EUR 16.0m at 30 June 2026 (31 Dec 2025: 12.4) against cash of 100.7; no amounts under the green facility repayable within twelve months. | C9: S4 | D9: 27 | E9: F1886
B10: Fast Places Limited (51%) is not consolidated: shared power under the joint arrangement limits Fastned's ability to direct the relevant activities. | C10: S4 | D10: 32 | E10: F1887
B11: Directors state the 12-18 month liquidity forecasts show 'adequate funds' and adopt the going concern basis; losses in early years funded by borrowings and certificate issues via FAST Foundation. | C11: S4 | D11: 33 | E11: F1888
B12: Company states it invests in new stations, chargers and grid connections only if financing for those investments is secured. | C12: S4 | D12: 33 | E12: F1889
B13: Approximately EUR 5m of Q1 2026 Dutch e-credit sales could not be recognised at 30 June 2026 because the national government registry was not operational. | C13: S4 | D13: 35 | E13: F1890
... B105: Auditor inspected correspondence with regulators including the AFM and 'did not identify a potential non-compliance risk' with laws and regulations. | C105: S1 | D105: 181 | E105: F192

Sheet Facts
A1: fact_id | B1: block | C1: field | D1: label | E1: period | F1: value | G1: unit | H1: text | I1: source | J1: page | K1: quote | L1: status | M1: reviewer | N1: note | O1: link
A2: F001 | B2: identity | C2: legal_name | D2: Legal name | H2: Fastned B.V. | I2: S1 | J2: 177 | K2: We have audited the financial statements 2023 of Fastned B.V. | L2: ok | M2: Sam Lakmaker | O2: https://vanillabonds.com/dossier-data/pdf/fastned/fastned-2023-annual-report.pdf#page=177
A3: F002 | B3: identity | C3: legal_form | D3: Legal form | H3: Dutch B.V. (private limited company) | I3: S1 | J3: 61 | K3: Fastned B.V. (the “Company”) is a private liability company incorporated under Dutch law and listed on Euronext Amsterdam in the Netherlands. | L3: pend | O3: https://vanillabonds.com/dossier-data/pdf/fastned/fastned-2023-annual-report.pdf#page=61
A4: F003 | B4: identity | C4: legal_form | D4: Legal form | H4: Dutch B.V. (besloten vennootschap) | I4: S1 | J4: 177 | K4: We have audited the financial statements 2023 of Fastned B.V. (“Fastned” or the “Company”) based in Amsterdam. | L4: pend | O4: https://vanillabonds.com/dossier-data/pdf/fastned/fastned-2023-annual-report.pdf#page=177
A5: F004 | B5: identity | C5: registry | D5: Commercial register / registration no. | H5: KvK 54606179 | I5: S1 | J5: 97 | K5: registered with the Dutch trade register under number 54606179 | L5: pend | O5: https://vanillabonds.com/dossier-data/pdf/fastned/fastned-2023-annual-report.pdf#page=97
A6: F005 | B6: identity | C6: founded | D6: Founded | H6: 2012 | I6: S1 | J6: 8 | K6: When we founded Fastned in 2012, we were seen as pioneers and some questioned if we would ever be profitable. | L6: pend | O6: https://vanillabonds.com/dossier-data/pdf/fastned/fastned-2023-annual-report.pdf#page=8
A7: F006 | B7: identity | C7: registered_office | D7: Registered office | H7: Mondriaantoren, Amstelplein 44, Amsterdam | I7: S1 | J7: 97 | K7: The registered office is located at Mondriaantoren, floor 21 & 22, Amstelplein 44 in Amsterdam. | L7: pend | O7: https://vanillabonds.com/dossier-data/pdf/fastned/fastned-2023-annual-report.pdf#page=97
A8: F007 | B8: identity | C8: registered_office | D8: Registered office | H8: Amsterdam, Amstelplein 44, 1096 BC | I8: S1 | J8: 203 | K8: Mondriaantoren, floor 21 & 22, Amstelplein 44, 1096 BC Amsterdam | L8: pend | O8: https://vanillabonds.com/dossier-data/pdf/fastned/fastned-2023-annual-report.pdf#page=203
A9: F008 | B9: identity | C9: country | D9: Country of incorporation (ISO-2) | H9: NL | I9: S1 | J9: 177 | K9: (“Fastned” or the “Company”) based in Amsterdam. | L9: ok | M9: Sam Lakmaker | O9: https://vanillabonds.com/dossier-data/pdf/fastned/fastned-2023-annual-report.pdf#page=177
A10: F009 | B10: identity | C10: sector | D10: Sector | H10: EV fast charging station operator | I10: S1 | J10: 97 | K10: The principal activity of Fastned B.V. and subsidiaries (the Group) consist of the exploitation of fast charging facilities for fully electric and hybrid cars. | L10: pend | O10: https://vanillabonds.com/dossier-data/pdf/fastned/fastned-2023-annual-report.pdf#page=97
A11: F010 | B11: identity | C11: sector | D11: Sector | H11: EV fast-charging station construction and operation | I11: S1 | J11: 117 | K11: Construction and operating charging stations | L11: pend | O11: https://vanillabonds.com/dossier-data/pdf/fastned/fastned-2023-annual-report.pdf#page=117
A12: F011 | B12: identity | C12: sites | D12: Sites / countries of operation | H12: 297 stations, 9 countries (NL DE FR BE UK CH DK IT ES) | I12: S1 | J12: 18 | K12: Fastned is now active in nine countries. | L12: pend | O12: https://vanillabonds.com/dossier-data/pdf/fastned/fastned-2023-annual-report.pdf#page=18
A13: F012 | B13: identity | C13: sites | D13: Sites / countries of operation | H13: Seven countries of operation | I13: S1 | J13: 122 | K13: The Group operates in seven countries. | L13: pend | O13: https://vanillabonds.com/dossier-data/pdf/fastned/fastned-2023-annual-report.pdf#page=122
A14: F013 | B14: identity | C14: sites | D14: Sites / countries of operation | H14: Avg FTE 2023: NL 107, DE 17, FR 15, BE 14, UK 12, CH 4, IT/ES/DK 1 | I14: S1 | J14: 123 | K14: In the Netherlands, the average number of employees was 107 (2022: 75). The other countries are split as follow: Belgium 14 (2022: 6), Switzerland 4 (2022: 2), Germany 17 (2022: 12), France 15 | L14: pend | O14: https://vanillabonds.com/dossier-data/pdf/fastned/fastned-2023-annual-report.pdf#page=123
A15: F014 | B15: identity | C15: employees | D15: Employees (FTE, period end) | E15: FY2022 | F15: 146 | H15: Headcount at year-end 2022; FTE not stated. | I15: S1 | J15: 31 | K15: We added 76 people to the team, as our organisation grew from 146 to 222 employees by year-end, with an average age of 35, ranging from 23 to 61. | L15: pend | N15: conflict: S1·p31 146 vs S1·p123 114 | O15: https://vanillabonds.com/dossier-data/pdf/fastned/fastned-2023-annual-report.pdf#page=31
A16: F015 | B16: identity | C16: employees | D16: Employees (FTE, period end) | E16: FY2022 | F16: 114 | H16: Average number of FTEs of the Group in 2022 (average, not period end) | I16: S1 | J16: 123 | K16: In 2023, the average number of FTEs of the Group was 172 (2022 : 114). | L16: pend | N16: conflict: S1·p31 146 vs S1·p123 114 | O16: https://vanillabonds.com/dossier-data/pdf/fastned/fastned-2023-annual-report.pdf#page=123
A17: F016 | B17: identity | C17: employees | D17: Employees (FTE, period end) | E17: FY2023 | F17: 222 | H17: Headcount at year-end 2023 (204 full-time, 18 part-time); FTE not stated. | I17: S1 | J17: 31 | K17: We added 76 people to the team, as our organisation grew from 146 to 222 employees by year-end, with an average age of 35, ranging from 23 to 61. | L17: pend | N17: conflict: S1·p31 222 vs S1·p123 172 vs S2·p134 172 | O17: https://vanillabonds.com/dossier-data/pdf/fastned/fastned-2023-annual-report.pdf#page=31
A18: F017 | B18: identity | C18: employees | D18: Employees (FTE, period end) | E18: FY2023 | F18: 172 | H18: Average number of FTEs of the Group in 2023 (average, not period end) | I18: S1 | J18: 123 | K18: In 2023, the average number of FTEs of the Group was 172 (2022 : 114). | L18: pend | N18: conflict: S1·p31 222 vs S1·p123 172 vs S2·p134 172 | O18: https://vanillabonds.com/dossier-data/pdf/fastned/fastned-2023-annual-report.pdf#page=123
A19: F018 | B19: identity | C19: ownership | D19: Ownership / UBO | H19: FAST holds all shares, DRs listed; Schroders >=10% of DRs | I19: S1 | J19: 64 | K19: FAST holds all shares of the Company (including those previously held by the founders and other major shareholders) and issues depository receipts (DRs) for these shares to investors and founders. | L19: pend | O19: https://vanillabonds.com/dossier-data/pdf/fastned/fastned-2023-annual-report.pdf#page=64
A20: F019 | B20: identity | C20: ownership | D20: Ownership / UBO | H20: Shares held by FAST (Fastned Administratie Stichting) | I20: S1 | J20: 118 | K20: Shares in Fastned B.V. are held by FAST (Fastned Administratie Stichting), Amsterdam. | L20: pend | O20: https://vanillabonds.com/dossier-data/pdf/fastned/fastned-2023-annual-report.pdf#page=118
A21: F020 | B21: identity | C21: ownership | D21: Ownership / UBO | H21: Wilhelmina-Dok B.V. (Bart Lubbers) 37.0% of DRs (2022: 39.2%) | I21: S1 | J21: 118 | K21: Wilhelmina-Dok B.V. (Bart Lubbers) 37.0 39.2 | L21: pend | O21: https://vanillabonds.com/dossier-data/pdf/fastned/fastned-2023-annual-report.pdf#page=118
A22: F021 | B22: identity | C22: ownership | D22: Ownership / UBO | H22: Carraig Aonair Holding B.V. (Langezaal) 21.5% (2022: 23.5%) | I22: S1 | J22: 118 | K22: Carraig Aonair Holding B.V. (Michiel Langezaal) 21.5 23.5 | L22: pend | O22: https://vanillabonds.com/dossier-data/pdf/fastned/fastned-2023-annual-report.pdf#page=118
A23: F022 | B23: identity | C23: ownership | D23: Ownership / UBO | H23: Breesaap B.V. 5.9% of shares; Bart Lubbers holds 33% of Breesaap | I23: S1 | J23: 118 | K23: Furthermore, Bart Lubbers has a 33% share in Breesaap B.V. Breesaap B.V. has 5.9% of shares in Fastned B.V. | L23: pend | O23: https://vanillabonds.com/dossier-data/pdf/fastned/fastned-2023-annual-report.pdf#page=118
A24: F023 | B24: identity | C24: listing | D24: Listings (equity, bonds) | H24: DRs on Euronext Amsterdam; retail bonds EUR 159.9m | I24: S1 | J24: 64 | K24: All DRs (100% of the Fastned share capital) are listed on Euronext Amsterdam. | L24: pend | O24: https://vanillabonds.com/dossier-data/pdf/fastned/fastned-2023-annual-report.pdf#page=64
A25: F024 | B25: identity | C25: listing | D25: Listings (equity, bonds) | H25: Bonds not registered on any exchange | I25: S1 | J25: 136 | K25: The bonds are not subordinated and trading is very limited as they are not registered on any exchange. | L25: pend | O25: https://vanillabonds.com/dossier-data/pdf/fastned/fastned-2023-annual-report.pdf#page=136
A26: F025 | B26: identity | C26: listing | D26: Listings (equity, bonds) | H26: Depositary receipts listed on Euronext; bonds unlisted | I26: S1 | J26: 150 | K26: Share price at Euronext (€) 34.18 | L26: pend | O26: https://vanillabonds.com/dossier-data/pdf/fastned/fastned-2023-annual-report.pdf#page=150
A27: F026 | B27: identity | C27: auditor | D27: Auditor | H27: BDO Audit & Assurance B.V. | I27: S1 | J27: 63 | K27: BDO Audit & Assurance B.V. was appointed as the external independent auditor for the financial years 2023 and 2024. | L27: pend | O27: https://vanillabonds.com/dossier-data/pdf/fastned/fastned-2023-annual-report.pdf#page=63
A28: F027 | B28: identity | C28: auditor | D28: Auditor | H28: BDO Audit & Assurance B.V. (2022: Deloitte Accountants B.V.) | I28: S1 | J28: 156 | K28: Group auditor for 2023 is BDO Audit & Assurance B.V. (2022: Deloitte Accountants B.V.). | L28: pend | O28: https://vanillabonds.com/dossier-data/pdf/fastned/fastned-2023-annual-report.pdf#page=156
A29: F028 | B29: identity | C29: audit_opinion | D29: Audit opinion | E29: FY2023 | H29: unqualified | I29: S1 | J29: 78 | K29: Attached to these statements is the unqualified independent auditor’s report from BDO Audit & Assurance B.V.. | L29: pend | O29: https://vanillabonds.com/dossier-data/pdf/fastned/fastned-2023-annual-report.pdf#page=78
A30: F029 | B30: identity | C30: audit_opinion | D30: Audit opinion | E30: FY2023 | H30: unqualified; consolidated statements give a true and fair view under EU-IFRS and Part 9 Book 2 DCC; no emphasis of matter | I30: S1 | J30: 178 | K30: In our opinion, the accompanying consolidated financial statements give a true and fair view of the financial position of Fastned B.V. as at 31 December 2023 | L30: pend | O30: https://vanillabonds.com/dossier-data/pdf/fastned/fastned-2023-annual-report.pdf#page=178
A31: F030 | B31: identity | C31: accounting_standard | D31: Accounting standard | H31: IFRS (EU) and Part 9 Book 2 Dutch Civil Code | I31: S1 | J31: 97 | K31: prepared in accordance with International Financial Reporting Standards (IFRS) as adopted by the European Union (EU) and also comply with the financial reporting requirements included in Part 9 | L31: pend | O31: https://vanillabonds.com/dossier-data/pdf/fastned/fastned-2023-annual-report.pdf#page=97
A32: F031 | B32: identity | C32: accounting_standard | D32: Accounting standard | H32: EU-IFRS and Part 9 of Book 2 Dutch Civil Code | I32: S1 | J32: 160 | K32: These financial statements have been prepared in accordance with International Financial Reporting Standards (IFRSs) as adopted by the European Union (EU) | L32: pend | O32: https://vanillabonds.com/dossier-data/pdf/fastned/fastned-2023-annual-report.pdf#page=160
A33: F032 | B33: identity | C33: fiscal_year_end | D33: Fiscal year end | H33: 31 December | I33: S1 | J33: 160 | K33: for the year ended 31 December 2023 | L33: pend | O33: https://vanillabonds.com/dossier-data/pdf/fastned/fastned-2023-annual-report.pdf#page=160
A34: F033 | B34: business | C34: business_fact | D34: Business fact | H34: 2023 volumes: 99.6 GWh sold (+92%), 4.0 million charging sessions (+74%), 1,714 chargers (+39%), 297 stations (+55), 755,289 active customers (+246%). | I34: S1 | J34: 4 | K34: Volume of energy sold 99.6 GWh +92% vs. 2022 | L34: pend | O34: https://vanillabonds.com/dossier-data/pdf/fastned/fastned-2023-annual-report.pdf#page=4
A35: F034 | B35: business | C35: business_fact | D35: Business fact | H35: Station uptime above 99%; Google Maps rating 4.4/5; Net Promoter Score 60 in 2023. | I35: S1 | J35: 19 | K35: Our rating of 4.4/5 on Google Maps and our 2023 Net Promoter Score of 60 are evidence that our charging experience is highly valued by our customers. | L35: pend | O35: https://vanillabonds.com/dossier-data/pdf/fastned/fastned-2023-annual-report.pdf#page=19
A36: F035 | B36: business | C36: business_fact | D36: Business fact | H36: Awards 2023: Chargemap most reliable network in Europe (390,000 reviews), ZapMap best en-route public charging network UK, Autoblog favourite fast charging network NL. | I36: S1 | J36: 19 | K36: We've been named the 'best en-route public charging network' by ZapMap in the UK and the 'favourite fast charging network' by Autoblog in the Netherlands for two years in a row. | L36: pend | O36: https://vanillabonds.com/dossier-data/pdf/fastned/fastned-2023-annual-report.pdf#page=19
A37: F036 | B37: business | C37: business_fact | D37: Business fact | H37: Proprietary software platform Revolt runs network operations; app rated 4.7/5 (Apple) and 4.6/5 (Google Play); Apple CarPlay and Android Auto added in 2023. | I37: S1 | J37: 20 | K37: Revolt, our software platform developed in-house, forms the heart of our operations. | L37: pend | O37: https://vanillabonds.com/dossier-data/pdf/fastned/fastned-2023-annual-report.pdf#page=20
A38: F037 | B38: business | C38: business_fact | D38: Business fact | H38: Stations are designed, built, operated and maintained in-house; 55 new stations across seven countries in 2023; grid congestion slowed construction in NL, FR, BE and UK. | I38: S1 | J38: 21 | K38: Grid congestion is another factor that has slowed our construction pace in the Netherlands, France, Belgium and in the United Kingdom. | L38: pend | O38: https://vanillabonds.com/dossier-data/pdf/fastned/fastned-2023-annual-report.pdf#page=21
A39: F038 | B39: business | C39: business_fact | D39: Business fact | H39: Employees: 93 new hires and 17 leavers in 2023, turnover 9% (2022: 11%); 18 workers who are not employees; 38 nationalities; women 40% of workforce. | I39: S1 | J39: 32 | K39: This is backed up by our turnover of 9% in 2023, which is a decrease from 11% in the previous year. | L39: pend | O39: https://vanillabonds.com/dossier-data/pdf/fastned/fastned-2023-annual-report.pdf#page=32
A40: F039 | B40: business | C40: business_fact | D40: Business fact | H40: Operational EBITDA (gross profit from charging less network operation costs, non-IFRS) EUR 23.8m in 2023, 8.1m in 2022, 2.4m in 2021; margin 39% in 2023 (+17 pp). | I40: S1 | J40: 36 | K40: Operational EBITDA 23.8 8.1 2.4 194 % | L40: pend | O40: https://vanillabonds.com/dossier-data/pdf/fastned/fastned-2023-annual-report.pdf#page=36
A41: F040 | B41: business | C41: business_fact | D41: Business fact | H41: Network expansion costs EUR 15.2m in 2023 (2022: 12.0; 2021: 6.8), up 27% on more employees in expansion. | I41: S1 | J41: 36 | K41: Network expansion costs (15.2) (12.0) (6.8) 27 % | L41: pend | O41: https://vanillabonds.com/dossier-data/pdf/fastned/fastned-2023-annual-report.pdf#page=36
A42: F041 | B42: business | C42: business_fact | D42: Business fact | H42: Gross profit related to charging EUR 44.9m in 2023 (+119%), margin 74% (2022: 57%). | I42: S1 | J42: 36 | K42: Gross profit related to charging increased by 119% to €44.9 million. | L42: pend | O42: https://vanillabonds.com/dossier-data/pdf/fastned/fastned-2023-annual-report.pdf#page=36
... A111: F110 | B111: business | C111: key_event | D111: Key event (M&A, financing, strategy) | H111: Auditor change: BDO Audit & Assurance B.V. engaged by the General Meeting as of the audit for financial year 2023, replacing Deloitte Accountants B.V. | I111: S1 | J111: 187 | K111: We were engaged by the General Meeting as auditor of Fastned B.V., as of the audit for financial year 2023. | L111: pend | O111: https://vanillabonds.com/dossier-data/pdf/fastned/fastned-2023-annual-report.pdf#page=187
A112: F111 | B112: financials | C112: revenue | D112: Revenue | E112: FY2019 | F112: 4.5 | G112: EUR m | H112: Revenues related to charging 2019 (five-year table, EUR 4,548k). | I112: S1 | J112: 71 | K112: Revenues related to charging (€ ‘000) 60,510 68 % 35,963 191 % 12,352 98 % 6,253 37 % 4,548 | L112: pend | O112: https://vanillabonds.com/dossier-data/pdf/fastned/fastned-2023-annual-report.pdf#page=71
A113: F112 | B113: financials | C113: revenue | D113: Revenue | E113: FY2020 | F113: 6.3 | G113: EUR m | H113: Revenues related to charging 2020 (five-year table, EUR 6,253k). | I113: S1 | J113: 71 | K113: Revenues related to charging (€ ‘000) 60,510 68 % 35,963 191 % 12,352 98 % 6,253 37 % 4,548 | L113: pend | O113: https://vanillabonds.com/dossier-data/pdf/fastned/fastned-2023-annual-report.pdf#page=71
A114: F113 | B114: financials | C114: revenue | D114: Revenue | E114: FY2021 | F114: 12.5 | G114: EUR m | H114: Total revenues 2021 per financial review key figures (charging 12.4 + other 0.1). | I114: S1 | J114: 36 | K114: Total revenues 60.5 36.0 12.5 68 % | L114: pend | O114: https://vanillabonds.com/dossier-data/pdf/fastned/fastned-2023-annual-report.pdf#page=36
A115: F114 | B115: financials | C115: revenue | D115: Revenue | E115: FY2022 | F115: 36 | G115: EUR m | H115: Total revenue 2022 (EUR 35,978k) | I115: S1 | J115: 118 | K115: Total revenue 60,514 35,978 | L115: pend | O115: https://vanillabonds.com/dossier-data/pdf/fastned/fastned-2023-annual-report.pdf#page=118
A116: F115 | B116: financials | C116: revenue | D116: Revenue | E116: FY2023 | F116: 60.5 | G116: EUR m | H116: Total revenue 2023 (EUR 60,514k) | I116: S1 | J116: 118 | K116: Total revenue 60,514 35,978 | L116: pend | O116: https://vanillabonds.com/dossier-data/pdf/fastned/fastned-2023-annual-report.pdf#page=118
A117: F116 | B117: financials | C117: ebitda | D117: EBITDA (as reported) | E117: FY2021 | F117: -12.6 | G117: EUR m | H117: EBITDA 2021 per financial review key figures. | I117: S1 | J117: 36 | K117: EBITDA 4.6 (4.6) (12.6) | L117: pend | O117: https://vanillabonds.com/dossier-data/pdf/fastned/fastned-2023-annual-report.pdf#page=36
A118: F117 | B118: financials | C118: ebitda | D118: EBITDA (as reported) | E118: FY2022 | F118: -4.6 | G118: EUR m | H118: EBITDA as reported by the CODM segment note, total group 2022 (EUR -4,557k) | I118: S1 | J118: 121 | K118: EBITDA 1,857 (501) (1,660) (1,084) (2,634) (535) (4,557) | L118: pend | O118: https://vanillabonds.com/dossier-data/pdf/fastned/fastned-2023-annual-report.pdf#page=121
A119: F118 | B119: financials | C119: ebitda | D119: EBITDA (as reported) | E119: FY2023 | F119: 4.6 | G119: EUR m | H119: EBITDA as reported by the CODM segment note, total group 2023 (EUR 4,579k) | I119: S1 | J119: 120 | K119: EBITDA 6,890 525 (809) 763 (2,246) (544) 4,579 | L119: pend | O119: https://vanillabonds.com/dossier-data/pdf/fastned/fastned-2023-annual-report.pdf#page=120
A120: F119 | B120: financials | C120: ebitda_adj | D120: EBITDA adjusted / underlying (as reported) | E120: FY2021 | F120: -4.4 | G120: EUR m | H120: Underlying company EBITDA 2021 (financial review key figures). | I120: S1 | J120: 36 | K120: Underlying company EBITDA 7.8 (4.0) (4.4) | L120: pend | O120: https://vanillabonds.com/dossier-data/pdf/fastned/fastned-2023-annual-report.pdf#page=36
A121: F120 | B121: financials | C121: ebitda_adj | D121: EBITDA adjusted / underlying (as reported) | E121: FY2022 | F121: -4 | G121: EUR m | H121: Underlying company EBITDA 2022. | I121: S1 | J121: 37 | K121: The metric reached €7.8 million in 2023, up from €(4.0) million in the previous year. | L121: pend | O121: https://vanillabonds.com/dossier-data/pdf/fastned/fastned-2023-annual-report.pdf#page=37
A122: F121 | B122: financials | C122: ebitda_adj | D122: EBITDA adjusted / underlying (as reported) | E122: FY2023 | F122: 7.8 | G122: EUR m | H122: Underlying company EBITDA (company definition: before exceptional items and gross profit on station construction for third parties). | I122: S1 | J122: 37 | K122: The metric reached €7.8 million in 2023, up from €(4.0) million in the previous year. | L122: pend | O122: https://vanillabonds.com/dossier-data/pdf/fastned/fastned-2023-annual-report.pdf#page=37
A123: F122 | B123: financials | C123: ebit | D123: EBIT / operating result | E123: FY2022 | F123: -14.4 | G123: EUR m | H123: Operating loss EUR -14,365k (IFRS). | I123: S1 | J123: 91 | K123: Operating loss (12,108) (14,365) | L123: pend | O123: https://vanillabonds.com/dossier-data/pdf/fastned/fastned-2023-annual-report.pdf#page=91
... A131: F130 | B131: financials | C131: net_interest | D131: Net finance cost | E131: FY2021 | F131: 6.2 | G131: EUR m | H131: Net finance cost 2021 per financial review key figures. | I131: S1 | J131: 36 | K131: Finance income/(cost) (6.8) (7.4) (6.2) | L131: pend | O131: https://vanillabonds.com/dossier-data/pdf/fastned/fastned-2023-annual-report.pdf#page=36
A132: F131 | B132: financials | C132: net_interest | D132: Net finance cost | E132: FY2022 | F132: 7.4 | G132: EUR m | H132: Net finance cost: finance costs EUR 7,607k less finance income EUR 222k (p.91). | I132: S1 | J132: 36 | K132: Finance income/(cost) (6.8) (7.4) (6.2) | L132: pend | N132: conflict: S1·p36 7.4 vs S1·p125 7.6 vs S2·p39 7.4 | O132: https://vanillabonds.com/dossier-data/pdf/fastned/fastned-2023-annual-report.pdf#page=36
A133: F132 | B133: financials | C133: net_interest | D133: Net finance cost | E133: FY2022 | F133: 7.6 | G133: EUR m | H133: Total finance costs 2022 EUR 7,607k (gross; finance income of EUR 222k shown separately) | I133: S1 | J133: 125 | K133: Total finance costs 9,624 7,607 | L133: pend | N133: conflict: S1·p36 7.4 vs S1·p125 7.6 vs S2·p39 7.4 | O133: https://vanillabonds.com/dossier-data/pdf/fastned/fastned-2023-annual-report.pdf#page=125
A134: F133 | B134: financials | C134: net_interest | D134: Net finance cost | E134: FY2023 | F134: 6.8 | G134: EUR m | H134: Net finance cost: finance costs EUR 9,624k less finance income EUR 2,821k (p.91); interest paid EUR 9,115k. | I134: S1 | J134: 36 | K134: Finance income/(cost) (6.8) (7.4) (6.2) | L134: pend | N134: conflict: S1·p36 6.8 vs S1·p125 9.6 vs S2·p39 6.8 vs S3·p45 6.8 | O134: https://vanillabonds.com/dossier-data/pdf/fastned/fastned-2023-annual-report.pdf#page=36
A135: F134 | B135: financials | C135: net_interest | D135: Net finance cost | E135: FY2023 | F135: 9.6 | G135: EUR m | H135: Total finance costs 2023 EUR 9,624k (gross; finance income of EUR 2,821k is shown separately in note 8.6) | I135: S1 | J135: 125 | K135: Total finance costs 9,624 7,607 | L135: pend | N135: conflict: S1·p36 6.8 vs S1·p125 9.6 vs S2·p39 6.8 vs S3·p45 6.8 | O135: https://vanillabonds.com/dossier-data/pdf/fastned/fastned-2023-annual-report.pdf#page=125
A136: F135 | B136: financials | C136: cfo | D136: Cash flow from operating activities | E136: FY2021 | F136: -10 | G136: EUR m | H136: Net cash flow from operating activities 2021 EUR -9,979k (financial review). | I136: S1 | J136: 38 | K136: Net cash flow from operating activities (3,141) (10,790) (9,979) | L136: pend | O136: https://vanillabonds.com/dossier-data/pdf/fastned/fastned-2023-annual-report.pdf#page=38
A137: F136 | B137: financials | C137: cfo | D137: Cash flow from operating activities | E137: FY2022 | F137: -10.8 | G137: EUR m | H137: Net cash flows from operating activities EUR -10,790k. | I137: S1 | J137: 95 | K137: Net cash flows from operating activities (3,141) (10,790) | L137: pend | O137: https://vanillabonds.com/dossier-data/pdf/fastned/fastned-2023-annual-report.pdf#page=95
A138: F137 | B138: financials | C138: cfo | D138: Cash flow from operating activities | E138: FY2023 | F138: -3.1 | G138: EUR m | H138: Net cash flows from operating activities EUR -3,141k (interest paid and received classified as operating). | I138: S1 | J138: 95 | K138: Net cash flows from operating activities (3,141) (10,790) | L138: pend | O138: https://vanillabonds.com/dossier-data/pdf/fastned/fastned-2023-annual-report.pdf#page=95
A139: F138 | B139: financials | C139: capex | D139: Capex (PP&E + intangibles) | E139: FY2021 | F139: 36.6 | G139: EUR m | H139: Net cash used in investing activities 2021 EUR -36,598k (financial review; capex = payments for PP&E and intangibles per company definition). | I139: S1 | J139: 38 | K139: Net cash flow used in investing activities (66,838) (67,492) (36,598) | L139: pend | O139: https://vanillabonds.com/dossier-data/pdf/fastned/fastned-2023-annual-report.pdf#page=38
A140: F139 | B140: financials | C140: capex | D140: Capex (PP&E + intangibles) | E140: FY2022 | F140: 67.5 | G140: EUR m | H140: Payments for PP&E and other intangible assets EUR 67,492k. | I140: S1 | J140: 95 | K140: Payments for property, plant and equipment and other intangible assets 11, 12 (66,838) (67,492) | L140: pend | N140: conflict: S1·p95 67.5 vs S1·p130 75.3 | O140: https://vanillabonds.com/dossier-data/pdf/fastned/fastned-2023-annual-report.pdf#page=95
A141: F140 | B141: financials | C141: capex | D141: Capex (PP&E + intangibles) | E141: FY2022 | F141: 75.3 | G141: EUR m | H141: Additions to property, plant and equipment 2022 (EUR 75,265k); intangible additions EUR 220k shown in note 11 | I141: S1 | J141: 130 | K141: Additions 823 67,100 6,810 532 75,265 | L141: pend | N141: conflict: S1·p95 67.5 vs S1·p130 75.3 | O141: https://vanillabonds.com/dossier-data/pdf/fastned/fastned-2023-annual-report.pdf#page=130
A142: F141 | B142: financials | C142: capex | D142: Capex (PP&E + intangibles) | E142: FY2023 | F142: 66.8 | G142: EUR m | H142: Payments for PP&E and other intangible assets EUR 66,838k (notes 11, 12). | I142: S1 | J142: 95 | K142: Payments for property, plant and equipment and other intangible assets 11, 12 (66,838) (67,492) | L142: pend | N142: conflict: S1·p95 66.8 vs S1·p130 63.1 vs S2·p104 66.8 vs S2·p141 63.1 | O142: https://vanillabonds.com/dossier-data/pdf/fastned/fastned-2023-annual-report.pdf#page=95
A143: F142 | B143: financials | C143: capex | D143: Capex (PP&E + intangibles) | E143: FY2023 | F143: 63.1 | G143: EUR m | H143: Additions to property, plant and equipment 2023 (EUR 63,066k); intangible additions EUR 304k shown in note 11 | I143: S1 | J143: 130 | K143: Additions 14 59,205 2,908 939 63,066 | L143: pend | N143: conflict: S1·p95 66.8 vs S1·p130 63.1 vs S2·p104 66.8 vs S2·p141 63.1 | O143: https://vanillabonds.com/dossier-data/pdf/fastned/fastned-2023-annual-report.pdf#page=130
A144: F143 | B144: financials | C144: cash | D144: Cash & equivalents | E144: FY2021 | F144: 128.6 | G144: EUR m | H144: Cash and cash equivalents at 31 December 2021 EUR 128,591k (financial review). | I144: S1 | J144: 38 | K144: Cash and cash equivalents at 31 December 126,604 149,538 128,591 | L144: pend | O144: https://vanillabonds.com/dossier-data/pdf/fastned/fastned-2023-annual-report.pdf#page=38
A145: F144 | B145: financials | C145: cash | D145: Cash & equivalents | E145: FY2022 | F145: 149.5 | G145: EUR m | H145: Cash at banks and on hand 31 Dec 2022 (EUR 149,538k) | I145: S1 | J145: 143 | K145: Total cash and cash equivalents 126,604 149,538 | L145: pend | O145: https://vanillabonds.com/dossier-data/pdf/fastned/fastned-2023-annual-report.pdf#page=143
A146: F145 | B146: financials | C146: cash | D146: Cash & equivalents | E146: FY2023 | F146: 126.6 | G146: EUR m | H146: Cash at banks and on hand 31 Dec 2023 (EUR 126,604k), incl. EUR 79.0m demand deposits | I146: S1 | J146: 143 | K146: Total cash and cash equivalents 126,604 149,538 | L146: pend | O146: https://vanillabonds.com/dossier-data/pdf/fastned/fastned-2023-annual-report.pdf#page=143
A147: F146 | B147: financials | C147: gross_debt | D147: Gross financial debt (bonds + loans, excl. leases) | E147: FY2022 | F147: 112.9 | G147: EUR m | H147: Total interest-bearing loans and borrowings 31 Dec 2022 (EUR 112,906k); excludes leases | I147: S1 | J147: 136 | K147: Total interest-bearing loans and borrowings 160,999 112,906 | L147: pend | O147: https://vanillabonds.com/dossier-data/pdf/fastned/fastned-2023-annual-report.pdf#page=136
A148: F147 | B148: financials | C148: gross_debt | D148: Gross financial debt (bonds + loans, excl. leases) | E148: FY2023 | F148: 161 | G148: EUR m | H148: Total interest-bearing loans and borrowings 31 Dec 2023 (EUR 160,999k): nine unsecured bonds plus two Caisse des Dépôts secured loans; excludes leases | I148: S1 | J148: 136 | K148: Total interest-bearing loans and borrowings 160,999 112,906 | L148: pend | O148: https://vanillabonds.com/dossier-data/pdf/fastned/fastned-2023-annual-report.pdf#page=136
A149: F148 | B149: financials | C149: lease_liabilities | D149: Lease liabilities | E149: FY2022 | F149: 9.8 | G149: EUR m | H149: Total lease liabilities 31 Dec 2022 (EUR 9,810k) | I149: S1 | J149: 145 | K149: Total lease liabilities 21,244 9,810 | L149: pend | O149: https://vanillabonds.com/dossier-data/pdf/fastned/fastned-2023-annual-report.pdf#page=145
A150: F149 | B150: financials | C150: lease_liabilities | D150: Lease liabilities | E150: FY2023 | F150: 21.2 | G150: EUR m | H150: Total lease liabilities 31 Dec 2023 (EUR 21,244k): current 2,168k, non-current 19,076k | I150: S1 | J150: 145 | K150: Total lease liabilities 21,244 9,810 | L150: pend | O150: https://vanillabonds.com/dossier-data/pdf/fastned/fastned-2023-annual-report.pdf#page=145
A151: F150 | B151: financials | C151: equity | D151: Total equity | E151: FY2021 | F151: 109.2 | G151: EUR m | H151: Total equity 2021 EUR 109,209k (financial review). | I151: S1 | J151: 38 | K151: Total equity 146,185 160,645 109,209 | L151: pend | O151: https://vanillabonds.com/dossier-data/pdf/fastned/fastned-2023-annual-report.pdf#page=38
A152: F151 | B152: financials | C152: equity | D152: Total equity | E152: FY2022 | F152: 160.6 | G152: EUR m | H152: Total equity EUR 160,645k. | I152: S1 | J152: 97 | K152: At balance sheet date this resulted in an equity amounting to € 146.2 million (2022: €160.6 million) and a cash level of €126.6 million (2022: €149.5 million). | L152: pend | O152: https://vanillabonds.com/dossier-data/pdf/fastned/fastned-2023-annual-report.pdf#page=97
A153: F152 | B153: financials | C153: equity | D153: Total equity | E153: FY2023 | F153: 146.2 | G153: EUR m | H153: Total equity EUR 146,185k incl. non-controlling interests EUR -12k. | I153: S1 | J153: 97 | K153: At balance sheet date this resulted in an equity amounting to € 146.2 million (2022: €160.6 million) and a cash level of €126.6 million (2022: €149.5 million). | L153: pend | O153: https://vanillabonds.com/dossier-data/pdf/fastned/fastned-2023-annual-report.pdf#page=97
A154: F153 | B154: financials | C154: total_assets | D154: Total assets | E154: FY2021 | F154: 214.6 | G154: EUR m | H154: Total assets 2021 EUR 214,603k (financial review). | I154: S1 | J154: 38 | K154: Total assets 357,539 315,230 214,603 | L154: pend | O154: https://vanillabonds.com/dossier-data/pdf/fastned/fastned-2023-annual-report.pdf#page=38
A155: F154 | B155: financials | C155: total_assets | D155: Total assets | E155: FY2022 | F155: 315.2 | G155: EUR m | H155: Total assets EUR 315,230k. | I155: S1 | J155: 93 | K155: Total assets 357,539 315,230 | L155: pend | O155: https://vanillabonds.com/dossier-data/pdf/fastned/fastned-2023-annual-report.pdf#page=93
A156: F155 | B156: financials | C156: total_assets | D156: Total assets | E156: FY2023 | F156: 357.5 | G156: EUR m | H156: Total assets EUR 357,539k. | I156: S1 | J156: 93 | K156: Total assets 357,539 315,230 | L156: pend | O156: https://vanillabonds.com/dossier-data/pdf/fastned/fastned-2023-annual-report.pdf#page=93
A157: F156 | B157: debt | C157: debt_instrument | D157: Debt instrument | F157: 159.9 | H157: Bonds placed with retail investors: total outstanding EUR 159.9 million at end 2023 (two issues in 2023 of EUR 22m and more than EUR 30m; coupons and maturities in note 14). | I157: S1 | J157: 17 | K157: The total outstanding amount of investments raised with retail investors has grown this year to €159.9 million. | L157: pend | O157: https://vanillabonds.com/dossier-data/pdf/fastned/fastned-2023-annual-report.pdf#page=17
A158: F157 | B158: debt | C158: debt_instrument | D158: Debt instrument | F158: 7.3 | H158: 6.0% unsecured corporate bond maturing 21/03/2024, EUR 7,304k outstanding at 31 Dec 2023 (2022: 8,748k), unsecured, not subordinated, no covenants, unlisted | I158: S1 | J158: 136 | K158: 6.0 21/03/2024 7,304 8,748 | L158: pend | O158: https://vanillabonds.com/dossier-data/pdf/fastned/fastned-2023-annual-report.pdf#page=136
A159: F158 | B159: debt | C159: debt_instrument | D159: Debt instrument | F159: 9.7 | H159: 6.0% unsecured corporate bond maturing 12/12/2024, EUR 9,659k at 31 Dec 2023 (2022: 12,177k), unsecured, unlisted | I159: S1 | J159: 136 | K159: 6.0 12/12/2024 9,659 12,177 | L159: pend | O159: https://vanillabonds.com/dossier-data/pdf/fastned/fastned-2023-annual-report.pdf#page=136
A160: F159 | B160: debt | C160: debt_instrument | D160: Debt instrument | F160: 16.2 | H160: 6.0% unsecured corporate bond maturing 28/07/2025, EUR 16,206k at 31 Dec 2023 (2022: 16,206k) | I160: S1 | J160: 136 | K160: 6.0 28/07/2025 16,206 16,206 | L160: pend | O160: https://vanillabonds.com/dossier-data/pdf/fastned/fastned-2023-annual-report.pdf#page=136
A161: F160 | B161: debt | C161: debt_instrument | D161: Debt instrument | F161: 21.2 | H161: 6.0% unsecured corporate bond maturing 19/11/2025, EUR 21,194k at 31 Dec 2023 (2022: 21,194k) | I161: S1 | J161: 136 | K161: 6.0 19/11/2025 21,194 21,194 | L161: pend | O161: https://vanillabonds.com/dossier-data/pdf/fastned/fastned-2023-annual-report.pdf#page=136
A162: F161 | B162: debt | C162: debt_instrument | D162: Debt instrument | F162: 30.4 | H162: 5.0% unsecured corporate bond maturing 06/12/2027 per note 14.3 (note 14.4 lists 12/12/26), EUR 30,357k at 31 Dec 2023 (2022: 30,358k) | I162: S1 | J162: 136 | K162: 5.0 06/12/2027 30,357 30,358 | L162: pend | O162: https://vanillabonds.com/dossier-data/pdf/fastned/fastned-2023-annual-report.pdf#page=136
A163: F162 | B163: debt | C163: debt_instrument | D163: Debt instrument | F163: 13.2 | H163: 5.0% unsecured corporate bond maturing 21/12/2027 per note 14.3 (note 14.4 lists 21/06/27), EUR 13,248k at 31 Dec 2023 (2022: 13,237k) | I163: S1 | J163: 136 | K163: 5.0 21/12/2027 13,248 13,237 | L163: pend | O163: https://vanillabonds.com/dossier-data/pdf/fastned/fastned-2023-annual-report.pdf#page=136
A164: F163 | B164: debt | C164: debt_instrument | D164: Debt instrument | F164: 24.4 | H164: 5.5% unsecured corporate bond issued June 2023 maturing 12/06/2028, EUR 24,413k at 31 Dec 2023 (EUR 22.0m new money plus 2.4m extensions), interest quarterly in arrears | I164: S1 | J164: 136 | K164: 5.5 12/06/2028 24,413 — | L164: pend | O164: https://vanillabonds.com/dossier-data/pdf/fastned/fastned-2023-annual-report.pdf#page=136
A165: F164 | B165: debt | C165: debt_instrument | D165: Debt instrument | F165: 34.5 | H165: 6.0% unsecured corporate bond issued October 2023 maturing 16/10/2028, EUR 34,537k at 31 Dec 2023 (EUR 31.0m new money plus 3.5m extensions), interest quarterly in arrears | I165: S1 | J165: 136 | K165: 6.0 16/10/2028 34,537 — | L165: pend | O165: https://vanillabonds.com/dossier-data/pdf/fastned/fastned-2023-annual-report.pdf#page=136
A166: F165 | B166: debt | C166: debt_instrument | D166: Debt instrument | F166: 2.2 | H166: 4% secured loan from Caisse des Dépôts maturing 01/12/2031, EUR 2,160k at 31 Dec 2023 (2022: 2,077k); 4% fixed capitalised for two years, then a variable component based on kWh sold | I166: S1 | J166: 136 | K166: 4% secured loan 4.0 01/12/2031 2,160 2,077 | L166: pend | O166: https://vanillabonds.com/dossier-data/pdf/fastned/fastned-2023-annual-report.pdf#page=136
A167: F166 | B167: debt | C167: debt_instrument | D167: Debt instrument | F167: 1.9 | H167: 4% secured loan from Caisse des Dépôts maturing 01/12/2032, EUR 1,921k drawn in 2023 | I167: S1 | J167: 136 | K167: 4% secured loan 4.0 01/12/2032 1,921 — | L167: pend | O167: https://vanillabonds.com/dossier-data/pdf/fastned/fastned-2023-annual-report.pdf#page=136
A168: F167 | B168: debt | C168: covenant | D168: Financial covenant / restriction | H168: No covenants apply to the bonds that could require early repayment; bonds are unsecured. | I168: S1 | J168: 136 | K168: There are no securities for the bonds and there are no covenants applicable that could require Fastned to repay any of the loans. | L168: pend | O168: https://vanillabonds.com/dossier-data/pdf/fastned/fastned-2023-annual-report.pdf#page=136
A169: F168 | B169: risk | C169: risk_fact | D169: Risk fact | H169: Regulatory: EV subsidies phased out in Germany slowed Q4 2023 EV sales; tender conditions and concession renewals under review; management trend 'unchanged (moderate)'. | I169: S1 | J169: 28 | K169: For example, EV subsidies were phased out in Germany, which slowed down the sales of EVs in the last quarter of 2023. | L169: pend | O169: https://vanillabonds.com/dossier-data/pdf/fastned/fastned-2023-annual-report.pdf#page=28
A170: F169 | B170: risk | C170: risk_fact | D170: Risk fact | H170: Management states a 'low-to-moderate' risk appetite for most categories; ISO 31000-based framework; internal audit function created in 2023 within Risk & Audit. | I170: S1 | J170: 50 | K170: Fastned has a low-to-moderate appetite for most risk categories despite taking an entrepreneurial approach. | L170: pend | O170: https://vanillabonds.com/dossier-data/pdf/fastned/fastned-2023-annual-report.pdf#page=50
A171: F170 | B171: risk | C171: risk_fact | D171: Risk fact | H171: Brand and IP: unique station design but intellectual property protection is 'challenging' (management); brand visibility a new moderate risk in 2023. | I171: S1 | J171: 53 | K171: The unique brand design differentiates Fastned from competitors, but intellectual property protection is challenging. | L171: pend | O171: https://vanillabonds.com/dossier-data/pdf/fastned/fastned-2023-annual-report.pdf#page=53
A172: F171 | B172: risk | C172: risk_fact | D172: Risk fact | H172: Grid constraints: longer lead times for grid connections, particularly in the Netherlands; mitigation by early requests, over-sized capacity, load balancing and batteries; management trend 'unchanged (moderate)'. | I172: S1 | J172: 54 | K172: Across the EU, the electricity grid is facing increasing capacity limitations, leading to longer lead times for obtaining new connections, particularly in the Netherlands. | L172: pend | O172: https://vanillabonds.com/dossier-data/pdf/fastned/fastned-2023-annual-report.pdf#page=54
A173: F172 | B173: risk | C173: risk_fact | D173: Risk fact | H173: Supply chain: dependency on charger suppliers and constructors; diversification incl. charger supplier EVBox; production slots for chargers secured; management trend 'decreased to moderate'. | I173: S1 | J173: 54 | K173: To reduce dependency on third-party suppliers, Fastned is diversifying its supplier and contractor portfolio, for example by engaging with the charger supplier EVBox. | L173: pend | O173: https://vanillabonds.com/dossier-data/pdf/fastned/fastned-2023-annual-report.pdf#page=54
A174: F173 | B174: risk | C174: risk_fact | D174: Risk fact | H174: Health and safety: management raised the risk to 'moderate/high' in 2023 with more construction sites; H&S audit done, H&S manager hired, external audit again in 2024. | I174: S1 | J174: 54 | K174: In 2023, an H&S audit was conducted and Fastned hired an H&S manager to support the further improvement of H&S within daily practices | L174: pend | O174: https://vanillabonds.com/dossier-data/pdf/fastned/fastned-2023-annual-report.pdf#page=54
A175: F174 | B175: risk | C175: risk_fact | D175: Risk fact | H175: Funding: management rates the funding risk 'low' and states the capital position covers expansion and financial commitments for the 'coming 12-18 months'; outstanding bonds need refinancing. | I175: S1 | J175: 55 | K175: Fastned is focused on maintaining a healthy cash position to meet going concern and refinance outstanding bonds. | L175: pend | O175: https://vanillabonds.com/dossier-data/pdf/fastned/fastned-2023-annual-report.pdf#page=55
...

Sheet Documents
A1: Source | B1: Kind | C1: Period | D1: Date | E1: Origin | F1: Audited | G1: Pages | H1: Link
A2: S1 | B2: annual report | C2: FY2023 | D2: 2024-03-27 | E2: Fastned B.V. | F2: TRUE | G2: 203 | H2: https://vanillabonds.com/dossier-data/pdf/fastned/fastned-2023-annual-report.pdf
A3: S2 | B3: annual report | C3: FY2024 | D3: 2025-03-27 | E3: Fastned B.V. | F3: TRUE | G3: 207 | H3: https://vanillabonds.com/dossier-data/pdf/fastned/fastned-2024-annual-report.pdf
A4: S3 | B4: annual report | C4: FY2025 | D4: 2026-03-19 | E4: Fastned B.V. | F4: TRUE | G4: 246 | H4: https://vanillabonds.com/dossier-data/pdf/fastned/fastned-2025-annual-report.pdf
A5: S4 | B5: interim report | C5: H1-2026 | D5: 2026-08-13 | E5: Fastned B.V. (Management Board) | F5: FALSE | G5: 52 | H5: https://vanillabonds.com/dossier-data/pdf/fastned/fastned-h1-2026-interim-report.pdf
