Workbook

Sheet README
A1: Item | B1: Value
A2: Issuer | B2: Katjes International GmbH & Co. KG
A3: Data as of | B3: H1-2026
A4: Written | B4: 2026-10-22
A5: Units | B5: EUR m unless stated; days and headcount as counts; ratios as decimals
A6: Signs | B6: profits positive, losses negative; net interest = net finance cost, positive; capex and D&A positive
A7: Periods | B7: FY2025 = fiscal year ending in 2025; H1-2026 = half-year to 30 June 2026; FY2027E = a plan year or an amount falling due then (company figures)
A8: Record | B8: one value per field and period: approved before pending, audited before unaudited, the later report wins where restated (mvp/screen.py)
A9: Status | B9: ok = approved by a named reviewer; rep = management representation, attested by a named officer; pend = extracted, pending review; rej = rejected; grey cell = pending, gold cell = management representation
A10: Sources | B10: every number links to its row in Facts; the row links to the page of the published PDF or to the web source
A11: Formulas | B11: Ratios are live Excel formulas on the Financials cells, the same formulas as the platform; one-off income = the items in Bridge
A12: Scope | B12: facts and arithmetic on printed formulas only: no rating, no score, no recommendation. Demo built from the company's public reports.

Sheet Financials
A1: EUR m unless stated | B1: FY2019 | C1: FY2020 | D1: FY2021 | E1: FY2022 | F1: FY2023 | G1: FY2024 | H1: FY2025 | I1: FY2026 | J1: H1-2025 | K1: H1-2026 | L1: FY2024E | M1: FY2025E | N1: FY2026E | O1: FY2027E | P1: FY2027E-FY2029E | Q1: FY2028E
A2: Identity
A3: Employees (FTE, period end) | E3: 980 | F3: 998 | G3: 1097 | H3: 1648 | J3: 1118 | K3: 1787
A4: Historical financials and quality of earnings
A5: Revenue | B5: 210 | C5: 218 | D5: 255 | E5: 295 | F5: 377 | G5: 392.6 | H5: 503 | J5: 164.8 | K5: 256 | M5: 400
A6: EBITDA (as reported) | B6: 23 | C6: 25 | D6: 41 | E6: 37 | F6: 40.8 | G6: 44.8 | H6: 98.8 | J6: 13.9 | K6: 15.8
A7: EBIT / operating result | E7: 22.2 | F7: 22.5 | G7: 25 | H7: 71.1 | J7: 3.7 | K7: -6.8
A8: Net result | E8: 14.8 | F8: 10.2 | G8: 3.2 | H8: 53.2 | J8: -1 | K8: -15.9
A9: Depreciation & amortisation | E9: 15.1 | F9: 18.1 | G9: 19.8 | H9: 27.2
A10: Net finance cost | E10: 6.4 | F10: 11.4 | G10: 11.6 | H10: 19.2 | J10: 4.1 | K10: 11.2
A11: Cash flow from operating activities | E11: 10.4 | F11: 31.8 | G11: 45.6 | H11: 19.1 | J11: -9.8 | K11: 1.1
A12: Capex (PP&E + intangibles) | E12: 8 | F12: 14.6 | G12: 18.8 | H12: 19.6 | J12: 7 | K12: 8.3
A13: Cash & equivalents | E13: 35.5 | F13: 58.4 | G13: 54 | H13: 146.8 | J13: 38.4 | K13: 74.1
A14: Gross financial debt (bonds + loans, excl. leases) | E14: 173.5 | F14: 185.1 | G14: 176.2
A15: Lease liabilities | E15: 6.4 | F15: 6.8 | G15: 13.2 | H15: 74.7 | K15: 85.8
A16: Net debt (as reported) | E16: 138 | F16: 133.5 | G16: 135.4 | H16: 206
A17: Total equity | B17: 137.9 | C17: 139.5 | D17: 141.4 | E17: 167 | F17: 176 | G17: 176.2 | H17: 266.9 | J17: 175.3 | K17: 255.1
A18: Total assets | E18: 441.4 | F18: 477.6 | G18: 491.7 | H18: 812.3 | K18: 850.9
A19: Days from year end to filing of the accounts | F19: 87 | G19: 99 | H19: 92 | K19: 70
A20: Income taxes paid (cash flow statement) | E20: 2.6 | F20: 2.5 | G20: 2.5 | H20: 0.6 | J20: 0.3 | K20: 0.9
A21: Management
A22: Revenue as budgeted for that year (management plan at the time) | H22: 400 | I22: 650 | N22: 650
A23: Transaction, plan, projections and downside
A24: Debt principal falling due in the period | G24: 35.2 | L24: 35.2 | M24: 37.4 | N24: 74.3 | O24: 30.7 | P24: 136 | Q24: 185

Sheet Bridge
A1: Period | B1: One-off income inside EBITDA, as itemised in the reports | C1: EUR m counted | D1: Fact | E1: Rule
A2: FY2022 | B2: item: purchase price allocation effect (negative goodwill) oral care business recognised in other operating income at initial consolidation 7 Dec 2022; amount: 10.3; recurrence: 2022 | D2: F227 | E2: listed, not counted (10.3): may be part of the larger item counted
A3: FY2022 | B3: item: recognition of negative goodwill in profit or loss (other operating income); amount: 24.4; recurrence: 2022 only (2023: 0.0) | C3: 24.4 | D3: F228 | E3: counted
A4: FY2025 | B4: item: badwill from initial consolidation of Bogner (other operating income); amount: 35.1; recurrence: none | C4: 35.1 | D4: F837 | E4: counted
A5: FY2025 | B5: item: gain on disposal of the 23% CPK minority interest (other operating income); amount: 20.1; recurrence: none | C5: 20.1 | D5: F838 | E5: counted
A6: H1-2026 | B6: item: positive results from purchase price allocations in other operating result; amount: 13.8; recurrence: none in H1-2025 | D6: F1180 | E6: listed, not counted (13.8): total of the items counted
A7: H1-2026 | B7: item: badwill on the Graze acquisition, recognised in other operating income (preliminary PPA); amount: 11.2; recurrence: none stated | C7: 11.2 | D7: F1183 | E7: counted
A8: H1-2026 | B8: item: badwill on the Pastificio Plin acquisition, recognised in other operating income; amount: 2.6; recurrence: none stated | C8: 2.6 | D8: F1184 | E8: counted

Sheet Ratios
A1: Live formulas on Financials | B1: FY2019 | C1: FY2020 | D1: FY2021 | E1: FY2022 | F1: FY2023 | G1: FY2024 | H1: FY2025 | I1: H1-2025 | J1: H1-2026 | K1: Formula
A2: One-off income inside EBITDA | B2: =SUMIF(Bridge!$A:$A,"FY2019",Bridge!$C:$C) | C2: =SUMIF(Bridge!$A:$A,"FY2020",Bridge!$C:$C) | D2: =SUMIF(Bridge!$A:$A,"FY2021",Bridge!$C:$C) | E2: =SUMIF(Bridge!$A:$A,"FY2022",Bridge!$C:$C) | F2: =SUMIF(Bridge!$A:$A,"FY2023",Bridge!$C:$C) | G2: =SUMIF(Bridge!$A:$A,"FY2024",Bridge!$C:$C) | H2: =SUMIF(Bridge!$A:$A,"FY2025",Bridge!$C:$C) | I2: =SUMIF(Bridge!$A:$A,"H1-2025",Bridge!$C:$C) | J2: =SUMIF(Bridge!$A:$A,"H1-2026",Bridge!$C:$C) | K2: SUM of Bridge for the period
A3: EBITDA excluding one-off income | B3: =(Financials!B6-SUMIF(Bridge!$A:$A,"FY2019",Bridge!$C:$C)) | C3: =(Financials!C6-SUMIF(Bridge!$A:$A,"FY2020",Bridge!$C:$C)) | D3: =(Financials!D6-SUMIF(Bridge!$A:$A,"FY2021",Bridge!$C:$C)) | E3: =(Financials!E6-SUMIF(Bridge!$A:$A,"FY2022",Bridge!$C:$C)) | F3: =(Financials!F6-SUMIF(Bridge!$A:$A,"FY2023",Bridge!$C:$C)) | G3: =(Financials!G6-SUMIF(Bridge!$A:$A,"FY2024",Bridge!$C:$C)) | H3: =(Financials!H6-SUMIF(Bridge!$A:$A,"FY2025",Bridge!$C:$C)) | I3: =(Financials!J6-SUMIF(Bridge!$A:$A,"H1-2025",Bridge!$C:$C)) | J3: =(Financials!K6-SUMIF(Bridge!$A:$A,"H1-2026",Bridge!$C:$C)) | K3: EBITDA as reported − one-off income
A4: EBITDA margin excluding one-off income | B4: =IFERROR((Financials!B6-SUMIF(Bridge!$A:$A,"FY2019",Bridge!$C:$C))/Financials!B5,"") | C4: =IFERROR((Financials!C6-SUMIF(Bridge!$A:$A,"FY2020",Bridge!$C:$C))/Financials!C5,"") | D4: =IFERROR((Financials!D6-SUMIF(Bridge!$A:$A,"FY2021",Bridge!$C:$C))/Financials!D5,"") | E4: =IFERROR((Financials!E6-SUMIF(Bridge!$A:$A,"FY2022",Bridge!$C:$C))/Financials!E5,"") | F4: =IFERROR((Financials!F6-SUMIF(Bridge!$A:$A,"FY2023",Bridge!$C:$C))/Financials!F5,"") | G4: =IFERROR((Financials!G6-SUMIF(Bridge!$A:$A,"FY2024",Bridge!$C:$C))/Financials!G5,"") | H4: =IFERROR((Financials!H6-SUMIF(Bridge!$A:$A,"FY2025",Bridge!$C:$C))/Financials!H5,"") | I4: =IFERROR((Financials!J6-SUMIF(Bridge!$A:$A,"H1-2025",Bridge!$C:$C))/Financials!J5,"") | J4: =IFERROR((Financials!K6-SUMIF(Bridge!$A:$A,"H1-2026",Bridge!$C:$C))/Financials!K5,"") | K4: EBITDA excluding one-off income / revenue
A5: Free cash flow | E5: =IFERROR(Financials!E11-Financials!E12,"") | F5: =IFERROR(Financials!F11-Financials!F12,"") | G5: =IFERROR(Financials!G11-Financials!G12,"") | H5: =IFERROR(Financials!H11-Financials!H12,"") | I5: =IFERROR(Financials!J11-Financials!J12,"") | J5: =IFERROR(Financials!K11-Financials!K12,"") | K5: operating cash flow − capex
A6: Net debt excluding leases | E6: =(Financials!E14-Financials!E13) | F6: =(Financials!F14-Financials!F13) | G6: =(Financials!G14-Financials!G13) | K6: gross debt excluding leases − cash
A7: Net debt / EBITDA excluding one-off income | E7: =IFERROR((Financials!E14-Financials!E13)/(Financials!E6-SUMIF(Bridge!$A:$A,"FY2022",Bridge!$C:$C)),"") | F7: =IFERROR((Financials!F14-Financials!F13)/(Financials!F6-SUMIF(Bridge!$A:$A,"FY2023",Bridge!$C:$C)),"") | G7: =IFERROR((Financials!G14-Financials!G13)/(Financials!G6-SUMIF(Bridge!$A:$A,"FY2024",Bridge!$C:$C)),"") | K7: net debt excluding leases / EBITDA excluding one-off income; fiscal years
A8: EBITDA excluding one-off income / net interest | E8: =IFERROR((Financials!E6-SUMIF(Bridge!$A:$A,"FY2022",Bridge!$C:$C))/Financials!E10,"") | F8: =IFERROR((Financials!F6-SUMIF(Bridge!$A:$A,"FY2023",Bridge!$C:$C))/Financials!F10,"") | G8: =IFERROR((Financials!G6-SUMIF(Bridge!$A:$A,"FY2024",Bridge!$C:$C))/Financials!G10,"") | H8: =IFERROR((Financials!H6-SUMIF(Bridge!$A:$A,"FY2025",Bridge!$C:$C))/Financials!H10,"") | K8: EBITDA excluding one-off income / net finance cost; fiscal years
A9: Equity ratio | E9: =IFERROR(Financials!E17/Financials!E18,"") | F9: =IFERROR(Financials!F17/Financials!F18,"") | G9: =IFERROR(Financials!G17/Financials!G18,"") | H9: =IFERROR(Financials!H17/Financials!H18,"") | J9: =IFERROR(Financials!K17/Financials!K18,"") | K9: equity / total assets

Sheet Debt
A1: Period | B1: Item | C1: Source | D1: Page | E1: Fact
A2: FY2026E | B2: principal falling due: 74.3 | C2: S3 | D2: 57 | E2: F754
A3: FY2027E | B3: principal falling due: 30.7 | C3: S3 | D3: 57 | E3: F755
A4: FY2028E | B4: principal falling due: 185.0 | C4: S3 | D4: 57 | E4: F756
B5: INSTRUMENTS
B6: Corporate bond 2023/2028, EUR 200.0m nominal after the EUR 15m increase in May 2026 (Missoni); carrying amount 200.0, fair value 191.3 at 30 June 2026; coupon not stated in this report. | C6: S5 | D6: 21 | E6: F1091
B7: Acquisition financing (long-term bank loans) for part of the Graze purchase price, amount not stated separately. | C7: S5 | D7: 25 | E7: F1092
B8: Non-current interest-bearing loans EUR 51.0m at 30 June 2026 (amortised cost, fair value 51.0); includes acquisition financing for part of the Graze purchase price. | C8: S5 | D8: 42 | E8: F1093
B9: Current interest-bearing loans EUR 68.1m at 30 June 2026, increased by new short-term credit lines drawn during the period. | C9: S5 | D9: 42 | E9: F1094
B10: Bond 2023/2028: senior unsecured bearer bond, target EUR 110m (minimum EUR 80m), fixed coupon marketed at 6.25-7.50% p.a. paid semi-annually, issued 21 September 2023, due 21 September 2028, ISIN NO0012888769, denomination EUR 1,000. | C10: S4 | D10: 1 | E10: F950
B11: Bond 2019/2024 (ISIN DE000A2TST99): outstanding at the time of the term sheet and to be refinanced from the proceeds of the 2023/2028 bond; amount and coupon not stated here. | C11: S4 | D11: 1 | E11: F951
B12: Liabilities to banks total EUR 72.0m at 31 Dec 2025 (2024: 50.4) within financial liabilities of 352.8. | C12: S3 | D12: 58 | E12: F686
B13: Accrued interest liabilities relating to the bond EUR 3.5m at 31 Dec 2025 (2024: 2.1). | C13: S3 | D13: 58 | E13: F687
B14: Hire purchase liabilities EUR 8.2m at 31 Dec 2025, of which current 2.4 (2024: 6.7, current 5.5); interest expense hire purchases 0.3. | C14: S3 | D14: 58 | E14: F688
B15: Liability from the purchase option on the remaining 25% of Dulcioliva EUR 1.6m, fully recognised as exercise probability unchanged. | C15: S3 | D15: 58 | E15: F689
B16: Put option granted to Bogner non-controlling shareholders recognised as financial liability of EUR 5.5m since initial consolidation. | C16: S3 | D16: 58 | E16: F690
B17: 2023/2028 corporate bond, 6.75% fixed, issued September 2023 at EUR 115m, increased by EUR 70m in August 2025 to EUR 185.0m outstanding at 31 Dec 2025 (2024: 115.0); interest expense 2025 EUR 9.5m; no ISIN or security stated. | C17: S3 | D17: 63 | E17: F691
... B53: 2020 liquidity-support bank loan: total EUR 5.0m, EUR 1.7m outstanding at 31 Dec 2023, not from a development bank, majority secured by a state guarantee. | C53: S1 | D53: 72 | E53: F093
B54: COVENANTS AND TERMS
B55: covenant: debt incurrence test; formula: Nettoverschuldung (Net Debt) / EBITDA; threshold: 3.75x; direction: max; test frequency: on each incurrence of additional debt | C55: S4 | D55: 2 | E55: F970
B56: covenant: distribution test; formula: Nettoverschuldung (Net Debt) / EBITDA after the distribution; threshold: 3.75x; direction: max; test frequency: on each distribution to shareholders | C56: S4 | D56: 2 | E56: F971
B57: covenant: negative pledge basket; formula: liabilities secured on the assets of the issuer or group; threshold: EUR 1.0m or, if greater, 5% of EBITDA; direction: max | C57: S4 | D57: 2 | E57: F972
B58: Breach of the issuer's undertakings, or events such as non-compliance with certain financial ratios, gives bondholders termination rights, subject to cure periods and the further conditions of the bond terms. | C58: S4 | D58: 1 | E58: F952
B59: Undertakings restrict mergers or similar business combinations. | C59: S4 | D59: 1 | E59: F953
B60: Undertakings restrict disposals of assets. | C60: S4 | D60: 1 | E60: F954
B61: Undertakings restrict financial indebtedness (Financial Indebtedness). | C61: S4 | D61: 1 | E61: F955
B62: Debt incurrence test: additional financial indebtedness of the issuer is permitted only if Net Debt / EBITDA is below 3.75x. | C62: S4 | D62: 2 | E62: F956
B63: Distributions to shareholders, including repayments of and interest on shareholder loans, are permitted only if Net Debt / EBITDA remains below 3.75x after the distribution. | C63: S4 | D63: 2 | E63: F957
B64: Distributions remain permitted to the extent the shareholder bears a tax charge from its participation in the issuer. | C64: S4 | D64: 2 | E64: F958
B65: Negative pledge: the issuer and group may not grant security over their assets, with exceptions including secured liabilities of up to EUR 1m or, if greater, 5% of EBITDA. | C65: S4 | D65: 2 | E65: F959
B66: Cross default: the bonds become callable if financial liabilities of EUR 7.5m in aggregate are not paid by the issuer or group or become callable because of insolvency. | C66: S4 | D66: 2 | E66: F960
... B117: term: listing; value: Nordic ABM of the Oslo Stock Exchange, included end of January 2024 (within six months of issue) | C117: S1 | D117: 85 | E117: F322

Sheet Guidance
A1: Year | B1: Metric | C1: Guidance as stated | D1: Reported | E1: Facts
A2: FY2023 | B2: EBITDA | C2: Guidance for 2023 as stated: EBITDA margin 9–10%; actual 10.8% | D2: 40.8 · margin 10.8% | E2: F115, F368
A3: FY2023 | B3: Revenue | C3: Guidance for 2023 as stated: consolidated net sales EUR 350m–375m (raised during the year); actual 377.4 exceeded it | D3: 377.0 | E3: F114, F654
A4: FY2024 | B4: EBITDA | C4: Guidance for 2024: EBITDA margin forecast at 10% (upper end of the range, half-year 2024 report); actual margin 11.4%. | D4: 44.8 · margin 11.4% | E4: F426, F660
A5: FY2024 | B5: Revenue | C5: Guidance issued for 2024: consolidated revenues between EUR 390m and EUR 420m; actual 392.6. | D5: 392.6 | E5: F425, F655
A6: FY2025 | B6: EBITDA | C6: Guidance for 2025 as stated in the FY2024 report: EBITDA margin between 9% and 10% (no absolute figure). | D6: 98.8 · margin 19.6%; excluding one-off income 43.6, margin 8.7% | E6: F1254, F661
A7: FY2025 | B7: Revenue | C7: Guidance for 2025 was Group revenue of at least EUR 400m; actual 503.0 | D7: 503.0 | E7: F716, F656
A8: FY2026 | B8: EBITDA | C8: Guidance for 2026 as stated in the FY2025 report: EBITDA margin between 10% and 12% (no absolute figure). | D8: not yet reported | E8: F1255
A9: FY2026 | B9: Revenue | C9: Company guidance for FY2026: Group revenue of 'at least EUR 650 million', which management expects 'to meet or exceed'. | D9: not yet reported | E9: F1104

Sheet Management
A1: Topic | B1: Fact | C1: Fact id
A2: person: Stephan Milde | B2: Managing Director (CFO) since 2012; before: several years in investment banking at Deutsche Bank and Citigroup in London. | C2: F1101
A3: person: Bastian Fassin | B3: Managing Partner since 2004; until 2003 Marketing and Sales at Kraft Foods; until 2000 Roland Berger Strategy Consultants. | C3: F1102
A4: person: Tobias Bachmüller | B4: Managing Partner since 1996; until 1995 General Manager Kraft Foods (Milka); until 1992 Principal, The Boston Consulting Group. | C4: F1103
A5: owners | B5: Limited partnership capital EUR 1.0m: fixed capital shares Bastian Fassin 0.9 (2023: 0.5) and Tobias Bachmüller 0.1 (0.1); no personal guarantee, share pledge or family charter is mentioned. | C5: F503
A6: owners | B6: Limited partners' fixed capital shares: Bastian Fassin EUR 0.5m, Tobias Bachmüller EUR 0.1m (registered liability EUR 540k / EUR 60k); interest-bearing clearing accounts of the limited partners EUR 0.5m at 5.0%. | C6: F198
A7: lenders | B7: No covenant test result disclosed; management states covenant compliance is ensured through continuous monitoring of KPIs and forward-looking financial planning. | C7: F718
A8: lenders | B8: instrument: Anleihe 2019/2024 (ISIN DE000A2TST99); due: 2024; outcome: refinanced by the 2023/2028 bond as stated in its use of proceeds | C8: F969
A9: lenders | B9: instrument: 2019/2024 bond; due: 2024; outcome: refinanced early in 2023 at 100.5% by the 2023/2028 bond of EUR 115m at 6.75% | C9: F904
A10: lenders | B10: instrument: purchase-price liability for the Oral Care production site in Viersen, recognised as financial liability at 31 Dec 2023; amount: 6.4; due: 2024; outcome: repaid in 2024 | C10: F583
A11: lenders | B11: instrument: 2019/2024 corporate bond; amount: 110.0; due: 2024; outcome: refinanced early in September 2023 at 100.5% by the new 2023/2028 bond of EUR 115m at 6.75% | C11: F584
A12: changes | B12: role: CEO Bogner (subsidiary); person: Arne Freundt; joined: 2026-06-01; reason as stated: former PUMA CEO assumed leadership to develop the brand and its international expansion | C12: F1242
... A27: board | B27: name: Tobias Bachmüller; body: management; role: Managing Shareholder, shareholder of general partner Xaver Fassin International GmbH and limited partner; since: 1996; independent: no | C27: F189

Sheet Risks
A1: Period | B1: Risk as the company states it | C1: Source | D1: Page | E1: Fact
B2: Seasonality: the second half carries significantly higher revenue and is decisive for the full year; the Bogner companies reinforce this pattern. | C2: S5 | D2: 22 | E2: F1095
B3: Two instances of damage caused by third parties reduced H1-2026 operating result; the company states insurance coverage or a right of recourse 'generally exists' and expects resolution in H2-2026. | C3: S5 | D3: 23 | E3: F1096
B4: Financial result worsened to -11.2 from -4.1, attributed to the bond increase and acquisition financing for Bogner, Missoni and Graze. | C4: S5 | D4: 23 | E4: F1097
B5: Going concern: management states 'no risks threatening the Company's continued existence are identifiable at present or in the foreseeable future'. | C5: S5 | D5: 26 | E5: F1098
B6: No significant changes in opportunities and risks versus the 2025 consolidated financial statements (pages 30 to 34 of that report). | C6: S5 | D6: 26 | E6: F1099
B7: FX: cash held in GBP EUR 2.8m (0.5m) and in other currencies, mainly RUB, CHF and USD, EUR 8.6m (10.6m) at 30 June 2026; group includes Bogner Eastern Europe LLC, Moscow. | C7: S5 | D7: 41 | E7: F1100
B8: Operating cash flow fell to 19.1 (2024: 45.6), attributed among other factors to the Bogner Group's strongly seasonal working capital; inventories rose to 97.1 (51.3) and receivables to 100.6 (59.2). | C8: S3 | D8: 26 | E8: F701
B9: Management expects 'largely stable sales development' citing the low cyclicality of confectionery and body care; luxury goods (Bogner) are described as subject to 'significant risks'. | C9: S3 | D9: 30 | E9: F702
B10: FX: international raw material sourcing exposes the Group to foreign exchange risk, especially against the US dollar; USD purchases hedged with forwards (notional 92.0); RUB, GBP, USD, CAD, CHF rates applied. | C10: S3 | D10: 32 | E10: F703
B11: Group companies may be required to repay subsidies or other government grants (stated risk, no amount). | C11: S3 | D11: 32 | E11: F704
B12: Key-person risk: success depends on the expertise and experience of key management personnel and qualified employees (stated risk). | C12: S3 | D12: 32 | E12: F705
B13: Holding structure: Katjes International's earnings are primarily dependent on the results of its subsidiaries and portfolio companies, which it services for consideration. | C13: S3 | D13: 32 | E13: F706
... B51: Trade receivables of EUR 0.9m more than six months overdue were written off in full at 31 Dec 2023; impairment allowance 0.4 (2022: 1.2). | C51: S1 | D51: 70 | E51: F110

Sheet Facts
A1: fact_id | B1: block | C1: field | D1: label | E1: period | F1: value | G1: unit | H1: text | I1: source | J1: page | K1: quote | L1: status | M1: reviewer | N1: note | O1: link
A2: F001 | B2: identity | C2: legal_name | D2: Legal name | H2: Katjes International GmbH & Co. KG | I2: S1 | J2: 50 | K2: Katjes International GmbH & Co. KG (‘Katjes | L2: ok | M2: demo reviewer | O2: https://vanillabonds.com/dossier-data/pdf/katjes/katjes-2023-annual-report.pdf#page=50
A3: F002 | B3: identity | C3: legal_form | D3: Legal form | H3: German GmbH & Co. KG (limited partnership) | I3: S1 | J3: 50 | K3: is a limited partnership (Kommanditgesellschaft) | L3: ok | M3: demo reviewer | O3: https://vanillabonds.com/dossier-data/pdf/katjes/katjes-2023-annual-report.pdf#page=50
A4: F003 | B4: identity | C4: registry | D4: Commercial register / registration no. | H4: Amtsgericht Kleve HRA 1076 | I4: S1 | J4: 50 | K4: Court (Amtsgericht) under commercial register number HRA 1076 | L4: ok | M4: demo reviewer | O4: https://vanillabonds.com/dossier-data/pdf/katjes/katjes-2023-annual-report.pdf#page=50
A5: F004 | B5: identity | C5: founded | D5: Founded | H5: Established 2011 from predecessor companies | I5: S1 | J5: 9 | K5: Established in 2011 from predecessor companies, the Katjes Group consists of Katjes International GmbH & Co. | L5: ok | M5: demo reviewer | O5: https://vanillabonds.com/dossier-data/pdf/katjes/katjes-2023-annual-report.pdf#page=9
A6: F005 | B6: identity | C6: registered_office | D6: Registered office | H6: Dechant-Sprünken-Str. 53–57, 46446 Emmerich am Rhein | I6: S1 | J6: 50 | K6: Dechant-Sprünken-Str. 53–57 46446 Emmerich am Rhein Germany | L6: ok | M6: demo reviewer | O6: https://vanillabonds.com/dossier-data/pdf/katjes/katjes-2023-annual-report.pdf#page=50
A7: F006 | B7: identity | C7: country | D7: Country of incorporation (ISO-2) | H7: DE | I7: S1 | J7: 50 | K7: 46446 Emmerich am Rhein Germany | L7: ok | M7: demo reviewer | O7: https://vanillabonds.com/dossier-data/pdf/katjes/katjes-2023-annual-report.pdf#page=50
A8: F007 | B8: identity | C8: sector | D8: Sector | H8: FMCG: confectionery and personal care products | I8: S1 | J8: 81 | K8: The Katjes International Group, through its subsidiaries, is a manufacturer and supplier of FMCG | L8: ok | M8: demo reviewer | O8: https://vanillabonds.com/dossier-data/pdf/katjes/katjes-2023-annual-report.pdf#page=81
A9: F008 | B9: identity | C9: sites | D9: Sites / countries of operation | H9: Production and sales in Italy, Germany, UK, Netherlands | I9: S1 | J9: 50 | K9: were performed in the Group companies in Italy, Germany, the United Kingdom (UK) and the Netherlands. | L9: ok | M9: demo reviewer | O9: https://vanillabonds.com/dossier-data/pdf/katjes/katjes-2023-annual-report.pdf#page=50
A10: F009 | B10: identity | C10: employees | D10: Employees (FTE, period end) | E10: FY2022 | F10: 980 | H10: Average employees for the year (not period end): 980 | I10: S1 | J10: 50 | K10: The Company employed an average of 998 employees in the financial year 2023 (2022: 980) | L10: ok | M10: demo reviewer | O10: https://vanillabonds.com/dossier-data/pdf/katjes/katjes-2023-annual-report.pdf#page=50
A11: F010 | B11: identity | C11: employees | D11: Employees (FTE, period end) | E11: FY2023 | F11: 998 | H11: Average employees for the year (not period end): 998, of which 596 Germany, 373 Italy, 14 Netherlands, 15 UK | I11: S1 | J11: 50 | K11: The Company employed an average of 998 employees in the financial year 2023 (2022: 980) | L11: ok | M11: demo reviewer | O11: https://vanillabonds.com/dossier-data/pdf/katjes/katjes-2023-annual-report.pdf#page=50
A12: F011 | B12: identity | C12: ownership | D12: Ownership / UBO | H12: Bastian Fassin (EUR 540k) and Tobias Bachmüller (EUR 60k) | I12: S1 | J12: 50 | K12: partners are Bastian Fassin, with registered liability of EUR 540 thousand and Tobias Bachmüller | L12: ok | M12: demo reviewer | O12: https://vanillabonds.com/dossier-data/pdf/katjes/katjes-2023-annual-report.pdf#page=50
A13: F012 | B13: identity | C13: listing | D13: Listings (equity, bonds) | H13: Bond 2023/2028 on Nordic ABM, Oslo Stock Exchange (Jan 2024) | I13: S1 | J13: 85 | K13: the Nordic ABM of the Oslo Stock Exchange at the end of January 2024 as planned within six months of the issue | L13: ok | M13: demo reviewer | O13: https://vanillabonds.com/dossier-data/pdf/katjes/katjes-2023-annual-report.pdf#page=85
A14: F013 | B14: identity | C14: auditor | D14: Auditor | H14: EY GmbH & Co. KG Wirtschaftsprüfungsgesellschaft, Düsseldorf | I14: S1 | J14: 94 | K14: Düsseldorf, 27th March 2024 EY GmbH & Co. KG Wirtschaftsprüfungsgesellschaft | L14: ok | M14: demo reviewer | O14: https://vanillabonds.com/dossier-data/pdf/katjes/katjes-2023-annual-report.pdf#page=94
A15: F014 | B15: identity | C15: audit_opinion | D15: Audit opinion | E15: FY2023 | H15: unqualified; no reservations (Sec. 322 (3) HGB); no EoM | I15: S1 | J15: 91 | K15: Pursuant to Sec. 322 (3) Sentence 1 HGB, we declare that our audit has not led to any reservations | L15: ok | M15: demo reviewer | O15: https://vanillabonds.com/dossier-data/pdf/katjes/katjes-2023-annual-report.pdf#page=91
A16: F015 | B16: identity | C16: accounting_standard | D16: Accounting standard | H16: IFRS as adopted by the EU plus Sec. 315e (1) HGB | I16: S1 | J16: 51 | K16: (IFRS) as adopted by the EU and the supplementary provisions set out in section 315e (1) of the German Commercial Code (HGB). | L16: ok | M16: demo reviewer | O16: https://vanillabonds.com/dossier-data/pdf/katjes/katjes-2023-annual-report.pdf#page=51
A17: F016 | B17: identity | C17: fiscal_year_end | D17: Fiscal year end | H17: 31 December (calendar year) | I17: S1 | J17: 50 | K17: The financial year is the calendar year. | L17: ok | M17: demo reviewer | O17: https://vanillabonds.com/dossier-data/pdf/katjes/katjes-2023-annual-report.pdf#page=50
A18: F017 | B18: business | C18: business_fact | D18: Business fact | H18: Activities are focused on Italy, Germany, the Netherlands, the UK, Spain and France through investments in local brands. | I18: S1 | J18: 9 | K18: activities are currently focused on Italy, Germany, the Netherlands, the UK, Spain and France. | L18: ok | M18: demo reviewer | O18: https://vanillabonds.com/dossier-data/pdf/katjes/katjes-2023-annual-report.pdf#page=9
A19: F018 | B19: business | C19: business_fact | D19: Business fact | H19: Dallmann's Pharma Candy produces Dallmann's sage throat lozenges and distributes WICK cough drops in Germany. | I19: S1 | J19: 17 | K19: Throat and cough drops / distribution of ‘WICK’ cough drops | L19: ok | M19: demo reviewer | O19: https://vanillabonds.com/dossier-data/pdf/katjes/katjes-2023-annual-report.pdf#page=17
A20: F019 | B20: business | C20: business_fact | D20: Business fact | H20: Katjes International is a strategic investor for more than a decade; sister companies Katjes Fassin GmbH + Co. KG (Katjes Germany) and Katjesgreenfood GmbH & Co. KG are legally independent and outside the consolidation. | I20: S1 | J20: 26 | K20: has been operating as a strategic investor for more than a decade. Together with its sister companies Katjes Fassin GmbH + Co. KG (‘Katjes Germany’) | L20: ok | M20: demo reviewer | O20: https://vanillabonds.com/dossier-data/pdf/katjes/katjes-2023-annual-report.pdf#page=26
A21: F020 | B21: business | C21: business_fact | D21: Business fact | H21: After an acquisition the associated companies remain legally and organisationally independent and local management is kept in place. | I21: S1 | J21: 26 | K21: associated companies remain independent in legal and organisational terms, and the local management is kept in place. | L21: ok | M21: demo reviewer | O21: https://vanillabonds.com/dossier-data/pdf/katjes/katjes-2023-annual-report.pdf#page=26
A22: F021 | B22: business | C22: business_fact | D22: Business fact | H22: Research and development expenses of the subsidiaries were EUR 1.0m in 2023 (2022: EUR 1.0m). | I22: S1 | J22: 28 | K22: reporting year, the corresponding expenses amounted to EUR 1.0 million (previous year: EUR 1.0 million) | L22: ok | M22: demo reviewer | O22: https://vanillabonds.com/dossier-data/pdf/katjes/katjes-2023-annual-report.pdf#page=28
A23: F022 | B23: business | C23: business_fact | D23: Business fact | H23: Product mix 2023: sugar confectionery 41.4% of sales (2022: 43.1%), body care 23.1% (18.8%), chocolate 15.7% (18.7%), seasonal 12.4% (12.6%). | I23: S1 | J23: 32 | K23: Chocolate products accounted for 15.7% (previous year: 18.7%) and seasonal products amounted to 12.4% (previous year: 12.6%). | L23: ok | M23: demo reviewer | O23: https://vanillabonds.com/dossier-data/pdf/katjes/katjes-2023-annual-report.pdf#page=32
A24: F023 | B24: business | C24: business_fact | D24: Business fact | H24: Cost of sales EUR 295.5m = 78.3% of revenue (2022: 82.6%); gross profit EUR 81.9m, gross margin 21.7% (2022: 17.4%). | I24: S1 | J24: 32 | K24: At 78.3%, cost of sales as a percentage of revenue was below the previous year’s level (2022: 82.6%). | L24: ok | M24: demo reviewer | O24: https://vanillabonds.com/dossier-data/pdf/katjes/katjes-2023-annual-report.pdf#page=32
A25: F024 | B25: business | C25: business_fact | D25: Business fact | H25: Equity ratio 36.9% at 31 Dec 2023 (2022: 37.8%), described by management as 'stable'. | I25: S1 | J25: 34 | K25: equity ratio remained stable at 36.9% as at the reporting date (31 December 2022: 37.8%). | L25: ok | M25: demo reviewer | O25: https://vanillabonds.com/dossier-data/pdf/katjes/katjes-2023-annual-report.pdf#page=34
A26: F025 | B26: business | C26: business_fact | D26: Business fact | H26: Raw material price risks are monitored through joint purchasing with Katjes Germany and the subsidiaries; short-term price risk managed by longer-term fixed-price supplier contracts. | I26: S1 | J26: 40 | K26: Risks relating to raw material prices are monitored as part of the joint purchasing activities with Katjes Germany | L26: ok | M26: demo reviewer | O26: https://vanillabonds.com/dossier-data/pdf/katjes/katjes-2023-annual-report.pdf#page=40
A27: F026 | B27: business | C27: business_fact | D27: Business fact | H27: Cash flow from investing activities EUR -14.6m in 2023 (2022: EUR -28.8m), including the cash outflow for the N.A.E. brand; 2022 included EUR 20.9m acquisition of subsidiaries. | I27: S1 | J27: 48 | K27: Cash flow from investing activities -14.6 -28.8 | L27: ok | M27: demo reviewer | O27: https://vanillabonds.com/dossier-data/pdf/katjes/katjes-2023-annual-report.pdf#page=48
... A40: F039 | B40: business | C40: key_event | D40: Key event (M&A, financing, strategy) | H40: End of January 2024: the 2023/2028 bond, structured as a Nordic bond for the first time, was included in the Nordic ABM of the Oslo Stock Exchange within six months of issue. | I40: S1 | J40: 85 | K40: The Katjes International 2023/2028 bond, which was for the first time structured as a Nordic bond, was included in | L40: ok | M40: demo reviewer | O40: https://vanillabonds.com/dossier-data/pdf/katjes/katjes-2023-annual-report.pdf#page=85
A41: F040 | B41: financials | C41: revenue | D41: Revenue | E41: FY2019 | F41: 210 | G41: EUR m | H41: From the five-year sales chart (rounded to EUR m) | I41: S1 | J41: 7 | K41: 210 218 255 295 2019 2020 2021 2022 2023 377 | L41: ok | M41: demo reviewer | O41: https://vanillabonds.com/dossier-data/pdf/katjes/katjes-2023-annual-report.pdf#page=7
A42: F041 | B42: financials | C42: revenue | D42: Revenue | E42: FY2020 | F42: 218 | G42: EUR m | H42: From the five-year sales chart (rounded to EUR m) | I42: S1 | J42: 7 | K42: 210 218 255 295 2019 2020 2021 2022 2023 377 | L42: ok | M42: demo reviewer | O42: https://vanillabonds.com/dossier-data/pdf/katjes/katjes-2023-annual-report.pdf#page=7
A43: F042 | B43: financials | C43: revenue | D43: Revenue | E43: FY2021 | F43: 255 | G43: EUR m | H43: From the five-year sales chart (rounded to EUR m) | I43: S1 | J43: 7 | K43: 210 218 255 295 2019 2020 2021 2022 2023 377 | L43: ok | M43: demo reviewer | O43: https://vanillabonds.com/dossier-data/pdf/katjes/katjes-2023-annual-report.pdf#page=7
A44: F043 | B44: financials | C44: revenue | D44: Revenue | E44: FY2022 | F44: 294.5 | G44: EUR m | H44: Consolidated revenue | I44: S1 | J44: 43 | K44: Revenue 377.4 294.5 | L44: ok | M44: demo reviewer | O44: https://vanillabonds.com/dossier-data/pdf/katjes/katjes-2023-annual-report.pdf#page=43
A45: F044 | B45: financials | C45: revenue | D45: Revenue | E45: FY2023 | F45: 377.4 | G45: EUR m | H45: Consolidated revenue | I45: S1 | J45: 43 | K45: Revenue 377.4 294.5 | L45: ok | M45: demo reviewer | O45: https://vanillabonds.com/dossier-data/pdf/katjes/katjes-2023-annual-report.pdf#page=43
A46: F045 | B46: financials | C46: revenue | D46: Revenue | E46: FY2024E | G46: EUR m | H46: Management guidance for 2024: consolidated sales between EUR 390m and EUR 420m (range, no point figure) | I46: S1 | J46: 41 | K46: company is expecting sales of between EUR 390 million and EUR 420 million for the financial year 2024. | L46: ok | M46: demo reviewer | O46: https://vanillabonds.com/dossier-data/pdf/katjes/katjes-2023-annual-report.pdf#page=41
A47: F046 | B47: financials | C47: ebitda | D47: EBITDA (as reported) | E47: FY2019 | F47: 23 | G47: EUR m | H47: From the five-year EBITDA chart (rounded to EUR m); year order read left to right | I47: S1 | J47: 7 | K47: 23 25 17 2019 2020 2021 2022 2023 37 41 | L47: ok | M47: demo reviewer | O47: https://vanillabonds.com/dossier-data/pdf/katjes/katjes-2023-annual-report.pdf#page=7
A48: F047 | B48: financials | C48: ebitda | D48: EBITDA (as reported) | E48: FY2020 | F48: 25 | G48: EUR m | H48: From the five-year EBITDA chart (rounded to EUR m); year order read left to right | I48: S1 | J48: 7 | K48: 23 25 17 2019 2020 2021 2022 2023 37 41 | L48: ok | M48: demo reviewer | O48: https://vanillabonds.com/dossier-data/pdf/katjes/katjes-2023-annual-report.pdf#page=7
A49: F048 | B49: financials | C49: ebitda | D49: EBITDA (as reported) | E49: FY2021 | F49: 17 | G49: EUR m | H49: From the five-year EBITDA chart (rounded to EUR m); year order read left to right | I49: S1 | J49: 7 | K49: 23 25 17 2019 2020 2021 2022 2023 37 41 | L49: pend | N49: conflict: S1·p7 17.0 vs S3·p7 41.0; primary per fact agent: open - no audited statement on file carries FY2021 EBITDA, and the chart text layers in S1 p7, S2 p7 and S3 p7 list bar values without a year for each bar; once FY2022 = 37.3 and FY2023 = 40.8 are taken out, S1 leaves 23, 25 or 17, S2 leaves 23 or 25 and S3 leaves 23 for FY2021, so a reviewer reads the chart images; the S1 FY2019 fact (23.0) depends on the same reading. | O49: https://vanillabonds.com/dossier-data/pdf/katjes/katjes-2023-annual-report.pdf#page=7
A50: F049 | B50: financials | C50: ebitda | D50: EBITDA (as reported) | E50: FY2022 | F50: 37.3 | G50: EUR m | H50: EBITDA as labelled in the management report | I50: S1 | J50: 32 | K50: amortisation) amounted to EUR 40.8 million in the financial year 2023 (2022: EUR 37.3 million) | L50: ok | M50: demo reviewer | O50: https://vanillabonds.com/dossier-data/pdf/katjes/katjes-2023-annual-report.pdf#page=32
A51: F050 | B51: financials | C51: ebitda | D51: EBITDA (as reported) | E51: FY2023 | F51: 40.8 | G51: EUR m | H51: EBITDA as labelled in the management report; EBITDA margin 10.8% (2022: 12.7%) | I51: S1 | J51: 32 | K51: amortisation) amounted to EUR 40.8 million in the financial year 2023 (2022: EUR 37.3 million) | L51: pend | N51: conflict: S1·p32 40.8 vs S2·p29 40.8 vs S3·p7 23.0; primary per fact agent: S2 p29 - S2 is the later audited report carrying FY2023 and its comparative equals S1 p32; S3 carries no FY2023 statement, and its 23.0 is a chart bar from p7 assigned to FY2023. | O51: https://vanillabonds.com/dossier-data/pdf/katjes/katjes-2023-annual-report.pdf#page=32
A52: F051 | B52: financials | C52: ebitda | D52: EBITDA (as reported) | E52: FY2024E | G52: EUR m | H52: Management guidance for 2024: EBITDA margin between 9% and 10% (no absolute figure) | I52: S1 | J52: 41 | K52: earnings, Katjes International is aiming for an EBITDA margin of between 9% and 10% in the financial year 2024. | L52: ok | M52: demo reviewer | O52: https://vanillabonds.com/dossier-data/pdf/katjes/katjes-2023-annual-report.pdf#page=41
A53: F052 | B53: financials | C53: ebit | D53: EBIT / operating result | E53: FY2022 | F53: 22.2 | G53: EUR m | H53: Operating result; 2022 includes EUR 24.4m negative goodwill in other operating income | I53: S1 | J53: 43 | K53: Operating result 22.5 22.2 | L53: ok | M53: demo reviewer | O53: https://vanillabonds.com/dossier-data/pdf/katjes/katjes-2023-annual-report.pdf#page=43
A54: F053 | B54: financials | C54: ebit | D54: EBIT / operating result | E54: FY2023 | F54: 22.5 | G54: EUR m | H54: Operating result | I54: S1 | J54: 43 | K54: Operating result 22.5 22.2 | L54: ok | M54: demo reviewer | O54: https://vanillabonds.com/dossier-data/pdf/katjes/katjes-2023-annual-report.pdf#page=43
A55: F054 | B55: financials | C55: net_income | D55: Net result | E55: FY2022 | F55: 14.8 | G55: EUR m | H55: Earnings after tax; attributable to Katjes International 15.2, non-controlling interests -0.4 | I55: S1 | J55: 43 | K55: Earnings after tax 10.2 14.8 | L55: ok | M55: demo reviewer | O55: https://vanillabonds.com/dossier-data/pdf/katjes/katjes-2023-annual-report.pdf#page=43
A56: F055 | B56: financials | C56: net_income | D56: Net result | E56: FY2023 | F56: 10.2 | G56: EUR m | H56: Earnings after tax; attributable to Katjes International 10.1, non-controlling interests 0.1 | I56: S1 | J56: 43 | K56: Earnings after tax 10.2 14.8 | L56: ok | M56: demo reviewer | O56: https://vanillabonds.com/dossier-data/pdf/katjes/katjes-2023-annual-report.pdf#page=43
A57: F056 | B57: financials | C57: da | D57: Depreciation & amortisation | E57: FY2022 | F57: 15.1 | G57: EUR m | H57: Depreciation and amortisation per expense breakdown | I57: S1 | J57: 78 | K57: Depreciation and amortisation 18.1 15.1 | L57: ok | M57: demo reviewer | O57: https://vanillabonds.com/dossier-data/pdf/katjes/katjes-2023-annual-report.pdf#page=78
A58: F057 | B58: financials | C58: da | D58: Depreciation & amortisation | E58: FY2023 | F58: 18.1 | G58: EUR m | H58: Depreciation and amortisation per expense breakdown (cash flow statement: 11.0 PP&E + 3.1 right-of-use + 4.2 intangibles) | I58: S1 | J58: 78 | K58: Depreciation and amortisation 18.1 15.1 | L58: ok | M58: demo reviewer | O58: https://vanillabonds.com/dossier-data/pdf/katjes/katjes-2023-annual-report.pdf#page=78
A59: F058 | B59: financials | C59: net_interest | D59: Net finance cost | E59: FY2022 | F59: 6.4 | G59: EUR m | H59: Financial result EUR -6.4m incl. at-equity loss share CPK -0.1; financial expenses 6.8 (bond interest 4.7, bank interest 1.2); interest paid 5.7 | I59: S1 | J59: 43 | K59: Financial result -11.4 -6.4 | L59: ok | M59: demo reviewer | O59: https://vanillabonds.com/dossier-data/pdf/katjes/katjes-2023-annual-report.pdf#page=43
A60: F059 | B60: financials | C60: net_interest | D60: Net finance cost | E60: FY2023 | F60: 11.4 | G60: EUR m | H60: Financial result EUR -11.4m incl. at-equity loss share CPK -0.7; financial expenses 12.0 (bond interest 6.5, bank interest 3.6, leasing 0.2, other 0.8), financial income 0.6; interest paid 8.1 | I60: S1 | J60: 43 | K60: Financial result -11.4 -6.4 | L60: ok | M60: demo reviewer | O60: https://vanillabonds.com/dossier-data/pdf/katjes/katjes-2023-annual-report.pdf#page=43
A61: F060 | B61: financials | C61: cfo | D61: Cash flow from operating activities | E61: FY2022 | F61: 10.4 | G61: EUR m | H61: Cash flow from operating activities | I61: S1 | J61: 48 | K61: Cash flow from operating activities 31.8 10.4 | L61: ok | M61: demo reviewer | O61: https://vanillabonds.com/dossier-data/pdf/katjes/katjes-2023-annual-report.pdf#page=48
A62: F061 | B62: financials | C62: cfo | D62: Cash flow from operating activities | E62: FY2023 | F62: 31.8 | G62: EUR m | H62: Cash flow from operating activities | I62: S1 | J62: 48 | K62: Cash flow from operating activities 31.8 10.4 | L62: ok | M62: demo reviewer | O62: https://vanillabonds.com/dossier-data/pdf/katjes/katjes-2023-annual-report.pdf#page=48
A63: F062 | B63: financials | C63: capex | D63: Capex (PP&E + intangibles) | E63: FY2022 | F63: 8 | G63: EUR m | H63: Additions to intangible assets (1.3) and PP&E (6.7) per fixed-asset schedule, excl. initial consolidation 77.5; cash flow shows PP&E -6.1 and intangibles -1.2 | I63: S1 | J63: 89 | K63: 232.4 8.0 77.5 0.0 -0.8 317.0 | L63: ok | M63: demo reviewer | O63: https://vanillabonds.com/dossier-data/pdf/katjes/katjes-2023-annual-report.pdf#page=89
A64: F063 | B64: financials | C64: capex | D64: Capex (PP&E + intangibles) | E64: FY2023 | F64: 14.3 | G64: EUR m | H64: Additions to intangible assets (6.4) and PP&E (7.9) per fixed-asset schedule, excl. right-of-use additions 3.5; cash flow shows PP&E -7.4 and intangibles -7.2 | I64: S1 | J64: 88 | K64: 317.0 14.3 0.0 0.0 -1.3 330.1 | L64: pend | N64: conflict: S1·p88 14.3 vs S2·p45 14.6; primary per fact agent: S2 p45 - S2 is the later audited report; its 2023 cash flow lines (-7.4 and -7.2) are the same lines S1's own cash flow statement shows, and S1's 14.3 is the fixed-asset schedule additions, a different line, not a restatement. | O64: https://vanillabonds.com/dossier-data/pdf/katjes/katjes-2023-annual-report.pdf#page=88
A65: F064 | B65: financials | C65: cash | D65: Cash & equivalents | E65: FY2022 | F65: 35.5 | G65: EUR m | H65: Cash and cash equivalents | I65: S1 | J65: 45 | K65: Cash and cash equivalents 6.7 58.4 35.5 | L65: ok | M65: demo reviewer | O65: https://vanillabonds.com/dossier-data/pdf/katjes/katjes-2023-annual-report.pdf#page=45
A66: F065 | B66: financials | C66: cash | D66: Cash & equivalents | E66: FY2023 | F66: 58.4 | G66: EUR m | H66: Cash and cash equivalents; includes EUR 2.0m in SEK (SEK 24.0m) | I66: S1 | J66: 45 | K66: Cash and cash equivalents 6.7 58.4 35.5 | L66: ok | M66: demo reviewer | O66: https://vanillabonds.com/dossier-data/pdf/katjes/katjes-2023-annual-report.pdf#page=45
A67: F066 | B67: financials | C67: gross_debt | D67: Gross financial debt (bonds + loans, excl. leases) | E67: FY2022 | F67: 173.5 | G67: EUR m | H67: Total financial liabilities as reported (prior-year figure adjusted for PPA finalisation), INCLUDING lease liabilities 6.4; bond 110.0, accrued interest 3.4, banks 42.5, hire-purchase 2.7 | I67: S1 | J67: 72 | K67: Total 191.9 173.5 | L67: ok | M67: demo reviewer | O67: https://vanillabonds.com/dossier-data/pdf/katjes/katjes-2023-annual-report.pdf#page=72
A68: F067 | B68: financials | C68: gross_debt | D68: Gross financial debt (bonds + loans, excl. leases) | E68: FY2023 | F68: 191.9 | G68: EUR m | H68: Total financial liabilities as reported (capital management table), INCLUDING lease liabilities 6.8; components: bond 115.0, accrued bond interest 2.1, liabilities to banks 56.3, Viersen site liability 6.4, hire-purchase 3.0, Dulcioliva option 1.2 | I68: S1 | J68: 72 | K68: Total 191.9 173.5 | L68: pend | N68: conflict: S1·p72 191.9 vs S2·p68 185.1; primary per fact agent: S2 p68 - No restatement: S2 shows the same FY2023 total of 191.9 as S1 p72; the S1 fact keeps the 6.8 lease liabilities inside, which the field excludes, so the S2 fact of 185.1 applies, a subtraction the reviewer confirms (it includes the 6.4 Viersen site liability). | O68: https://vanillabonds.com/dossier-data/pdf/katjes/katjes-2023-annual-report.pdf#page=72
A69: F068 | B69: financials | C69: lease_liabilities | D69: Lease liabilities | E69: FY2022 | F69: 6.4 | G69: EUR m | H69: IFRS 16 lease liabilities | I69: S1 | J69: 83 | K69: Due after five or more years 0.1 0.2 Total 6.8 6.4 | L69: ok | M69: demo reviewer | O69: https://vanillabonds.com/dossier-data/pdf/katjes/katjes-2023-annual-report.pdf#page=83
A70: F069 | B70: financials | C70: lease_liabilities | D70: Lease liabilities | E70: FY2023 | F70: 6.8 | G70: EUR m | H70: IFRS 16 lease liabilities: 2.9 due within one year, 3.8 one to five years, 0.1 after five years | I70: S1 | J70: 83 | K70: Due after five or more years 0.1 0.2 Total 6.8 6.4 | L70: ok | M70: demo reviewer | O70: https://vanillabonds.com/dossier-data/pdf/katjes/katjes-2023-annual-report.pdf#page=83
A71: F070 | B71: financials | C71: net_debt | D71: Net debt (as reported) | E71: FY2022 | F71: 138 | G71: EUR m | H71: Net debt as reported (adjusted) = financial liabilities 173.5 less cash 35.5; leverage ratio 45% | I71: S1 | J71: 64 | K71: Net debt 133.5 138.0 | L71: ok | M71: demo reviewer | O71: https://vanillabonds.com/dossier-data/pdf/katjes/katjes-2023-annual-report.pdf#page=64
A72: F071 | B72: financials | C72: net_debt | D72: Net debt (as reported) | E72: FY2023 | F72: 133.5 | G72: EUR m | H72: Net debt as reported = financial liabilities 191.9 (incl. leases) less cash 58.4; leverage ratio (net debt / total capital) 43% | I72: S1 | J72: 64 | K72: Net debt 133.5 138.0 | L72: ok | M72: demo reviewer | O72: https://vanillabonds.com/dossier-data/pdf/katjes/katjes-2023-annual-report.pdf#page=64
A73: F072 | B73: financials | C73: equity | D73: Total equity | E73: FY2019 | F73: 137.9 | G73: EUR m | H73: From the five-year equity chart | I73: S1 | J73: 8 | K73: 2019 2020 137.9 139.5 | L73: ok | M73: demo reviewer | O73: https://vanillabonds.com/dossier-data/pdf/katjes/katjes-2023-annual-report.pdf#page=8
A74: F073 | B74: financials | C74: equity | D74: Total equity | E74: FY2020 | F74: 139.5 | G74: EUR m | H74: From the five-year equity chart | I74: S1 | J74: 8 | K74: 2019 2020 137.9 139.5 | L74: ok | M74: demo reviewer | O74: https://vanillabonds.com/dossier-data/pdf/katjes/katjes-2023-annual-report.pdf#page=8
A75: F074 | B75: financials | C75: equity | D75: Total equity | E75: FY2021 | F75: 141.4 | G75: EUR m | H75: Total equity at 31 Dec 2021 per statement of changes in equity | I75: S1 | J75: 47 | K75: As at 31 Dec 2021 / 01 Jan 2022 0.6 2.0 2.0 129.5 0.9 2.1 0.2 2.3 137.3 4.1 141.4 | L75: ok | M75: demo reviewer | O75: https://vanillabonds.com/dossier-data/pdf/katjes/katjes-2023-annual-report.pdf#page=47
A76: F075 | B76: financials | C76: equity | D76: Total equity | E76: FY2022 | F76: 167 | G76: EUR m | H76: Total equity, prior-year figure adjusted for PPA finalisation (+7.7); shareholders' equity 164.1, NCI 2.9 | I76: S1 | J76: 46 | K76: Total equity 6.8 176.0 167.0 | L76: ok | M76: demo reviewer | O76: https://vanillabonds.com/dossier-data/pdf/katjes/katjes-2023-annual-report.pdf#page=46
A77: F076 | B77: financials | C77: equity | D77: Total equity | E77: FY2023 | F77: 176 | G77: EUR m | H77: Total equity; shareholders' equity 173.0, non-controlling interests 3.0 | I77: S1 | J77: 46 | K77: Total equity 6.8 176.0 167.0 | L77: ok | M77: demo reviewer | O77: https://vanillabonds.com/dossier-data/pdf/katjes/katjes-2023-annual-report.pdf#page=46
A78: F077 | B78: financials | C78: total_assets | D78: Total assets | E78: FY2022 | F78: 441.4 | G78: EUR m | H78: Total assets, prior-year figure adjusted for PPA finalisation; non-current 317.6, current 123.8 | I78: S1 | J78: 45 | K78: Total assets 477.6 441.4 | L78: ok | M78: demo reviewer | O78: https://vanillabonds.com/dossier-data/pdf/katjes/katjes-2023-annual-report.pdf#page=45
A79: F078 | B79: financials | C79: total_assets | D79: Total assets | E79: FY2023 | F79: 477.6 | G79: EUR m | H79: Total assets; non-current 313.0, current 164.6 | I79: S1 | J79: 45 | K79: Total assets 477.6 441.4 | L79: ok | M79: demo reviewer | O79: https://vanillabonds.com/dossier-data/pdf/katjes/katjes-2023-annual-report.pdf#page=45
A80: F079 | B80: debt | C80: debt_instrument | D80: Debt instrument | H80: Liabilities to banks total EUR 56.3m at 31 Dec 2023 (2022: EUR 42.5m); fair value equals carrying amount. | I80: S1 | J80: 64 | K80: liabilities to banks in the amount of EUR 56.3 million (2022: EUR 42.5 million) | L80: ok | M80: demo reviewer | O80: https://vanillabonds.com/dossier-data/pdf/katjes/katjes-2023-annual-report.pdf#page=64
A81: F080 | B81: debt | C81: debt_instrument | D81: Debt instrument | H81: Liability from the takeover of the Viersen production site (oral care division) EUR 6.4m, remaining purchase price due 2 January 2024. | I81: S1 | J81: 64 | K81: duction site for the oral care division in the amount of EUR 6.4 million is also included. | L81: ok | M81: demo reviewer | O81: https://vanillabonds.com/dossier-data/pdf/katjes/katjes-2023-annual-report.pdf#page=64
A82: F081 | B82: debt | C82: debt_instrument | D82: Debt instrument | H82: Hire-purchase contract liabilities EUR 3.0m (2022: 2.7). | I82: S1 | J82: 64 | K82: also include liabilities from hire-purchase contracts in the amount of EUR 3.0 million (2022: EUR 2.7 million). | L82: ok | M82: demo reviewer | O82: https://vanillabonds.com/dossier-data/pdf/katjes/katjes-2023-annual-report.pdf#page=64
A83: F082 | B83: debt | C83: debt_instrument | D83: Debt instrument | H83: Corporate bond 2023/2028, EUR 115.0m, fixed 6.75% (previous bond 4.25%), issued September 2023, maturity 2028, Nordic bond format, unsecured per reported terms not stated; carrying 115.0, fair value 123.1; accrued interest 2.1; bond interest expense 6.5 in 2023. | I83: S1 | J83: 69 | K83: Corporate bond 6.75 (previous year: 4.25) 115.0 110.0 | L83: ok | M83: demo reviewer | O83: https://vanillabonds.com/dossier-data/pdf/katjes/katjes-2023-annual-report.pdf#page=69
A84: F083 | B84: debt | C84: debt_instrument | D84: Debt instrument | H84: Bank loan facility kEUR 24,000 at 5.6%, EUR 24.0m outstanding at 31 Dec 2023 (2022: 15.0); management report attributes the increase to the acquisition loan for the oral care business (Viersen production facility). | I84: S1 | J84: 69 | K84: Bank loan kEUR 24.000 5.6 24.0 15.0 | L84: ok | M84: demo reviewer | O84: https://vanillabonds.com/dossier-data/pdf/katjes/katjes-2023-annual-report.pdf#page=69
A85: F084 | B85: debt | C85: debt_instrument | D85: Debt instrument | H85: Bank loan kEUR 11,700 at 2.9%, EUR 6.0m outstanding (2022: 8.2). | I85: S1 | J85: 69 | K85: Bank loan kEUR 11.700 2.9 6.0 8.2 | L85: ok | M85: demo reviewer | O85: https://vanillabonds.com/dossier-data/pdf/katjes/katjes-2023-annual-report.pdf#page=69
A86: F085 | B86: debt | C86: debt_instrument | D86: Debt instrument | H86: Bank loan kEUR 5,000 at 4.98%, EUR 5.0m outstanding (2022: 0.0), new in 2023. | I86: S1 | J86: 69 | K86: Bank loan kEUR 5.000 4.98 5.0 0.0 | L86: ok | M86: demo reviewer | O86: https://vanillabonds.com/dossier-data/pdf/katjes/katjes-2023-annual-report.pdf#page=69
A87: F086 | B87: debt | C87: debt_instrument | D87: Debt instrument | H87: Bank loan kEUR 5,000 at 8.5%, EUR 4.4m outstanding (2022: 0.0), new in 2023. | I87: S1 | J87: 69 | K87: Bank loan kEUR 5.000 8.5 4.4 0.0 | L87: ok | M87: demo reviewer | O87: https://vanillabonds.com/dossier-data/pdf/katjes/katjes-2023-annual-report.pdf#page=69
A88: F087 | B88: debt | C88: debt_instrument | D88: Debt instrument | H88: Bank loan kEUR 5,000 at 0.7%, EUR 1.7m outstanding (2022: 3.3); p72 reports a 2020 liquidity-support loan of EUR 5.0m with EUR 1.7m outstanding, secured by a state guarantee for the majority of the amount. | I88: S1 | J88: 69 | K88: Bank loan kEUR 5.000 0.7 1.7 3.3 | L88: ok | M88: demo reviewer | O88: https://vanillabonds.com/dossier-data/pdf/katjes/katjes-2023-annual-report.pdf#page=69
A89: F088 | B89: debt | C89: debt_instrument | D89: Debt instrument | H89: Bank loan kEUR 3,000 at 2.0%, EUR 1.1m outstanding (2022: 1.9). | I89: S1 | J89: 69 | K89: Bank loan kEUR 3.000 2.0 1.1 1.9 | L89: ok | M89: demo reviewer | O89: https://vanillabonds.com/dossier-data/pdf/katjes/katjes-2023-annual-report.pdf#page=69
A90: F089 | B90: debt | C90: debt_instrument | D90: Debt instrument | H90: Bank loan kEUR 3,000 at 1.8%, EUR 0.3m outstanding (2022: 0.9). | I90: S1 | J90: 69 | K90: Bank loan kEUR 3.000 1.8 0.3 0.9 | L90: ok | M90: demo reviewer | O90: https://vanillabonds.com/dossier-data/pdf/katjes/katjes-2023-annual-report.pdf#page=69
A91: F090 | B91: debt | C91: debt_instrument | D91: Debt instrument | H91: Bank loan kEUR 1,500 at 5.6%, EUR 0.0m outstanding at 31 Dec 2023 (2022: 1.5), repaid during 2023. | I91: S1 | J91: 69 | K91: Bank loan kEUR 1.500 5.6 0.0 1.5 | L91: ok | M91: demo reviewer | O91: https://vanillabonds.com/dossier-data/pdf/katjes/katjes-2023-annual-report.pdf#page=69
... A95: F094 | B95: risk | C95: risk_fact | D95: Risk fact | H95: Concentration risk from major customers, especially in food retail, named by management; retail and wholesale consolidation could change volumes and conditions. | I95: S1 | J95: 38 | K95: Concentration risks could arise from major customers, especially in the food retail sector. | L95: ok | M95: demo reviewer | O95: https://vanillabonds.com/dossier-data/pdf/katjes/katjes-2023-annual-report.pdf#page=38
A96: F095 | B96: risk | C96: risk_fact | D96: Risk fact | H96: Purchasing terms for sugar, cocoa, nuts, glucose and panthenol could become 'less favourable' and may not be passed on in prices. | I96: S1 | J96: 38 | K96: needed for production – especially sugar, cocoa, nuts, glucose and panthenol – could become less favourable. | L96: ok | M96: demo reviewer | N96: text: company wording put in quotation marks (reviewer, 20 Oct 2026) | O96: https://vanillabonds.com/dossier-data/pdf/katjes/katjes-2023-annual-report.pdf#page=38
A97: F096 | B97: risk | C97: risk_fact | D97: Risk fact | H97: Dependence on certain suppliers; delivery delays or non-delivery could cause production downtime. | I97: S1 | J97: 38 | K97: Katjes International is dependent on certain suppliers. Delivery delays or non-delivery by a supplier could lead to production downtime. | L97: ok | M97: demo reviewer | O97: https://vanillabonds.com/dossier-data/pdf/katjes/katjes-2023-annual-report.pdf#page=38
A98: F097 | B98: risk | C98: risk_fact | D98: Risk fact | H98: Management rates the overall market-related and regulatory risk as 'negligible' and company-related risks as 'manageable'; the opportunity and risk situation 'has not changed much' from the previous year. | I98: S1 | J98: 38 | K98: Katjes International considers the overall risk arising from the aforementioned market-related and regulatory risks to be negligible. | L98: ok | M98: demo reviewer | O98: https://vanillabonds.com/dossier-data/pdf/katjes/katjes-2023-annual-report.pdf#page=38
A99: F098 | B99: risk | C99: risk_fact | D99: Risk fact | H99: Geopolitical: the wars in Ukraine and the Middle East could cause further unrest in procurement markets and affect energy and raw material prices. | I99: S1 | J99: 38 | K99: The wars in Ukraine and the Middle East could cause | L99: ok | M99: demo reviewer | O99: https://vanillabonds.com/dossier-data/pdf/katjes/katjes-2023-annual-report.pdf#page=38
A100: F099 | B100: risk | C100: risk_fact | D100: Risk fact | H100: Group companies may have to repay subsidies or other government funding (government grants of about EUR 2.4m received in 2023). | I100: S1 | J100: 38 | K100: Group companies have to repay subsidies or other | L100: ok | M100: demo reviewer | O100: https://vanillabonds.com/dossier-data/pdf/katjes/katjes-2023-annual-report.pdf#page=38
A101: F100 | B101: risk | C101: risk_fact | D101: Risk fact | H101: Seasonality: the confectionery business is subject to seasonal fluctuations (Christmas and Easter specialities at Sperlari/Paluani). | I101: S1 | J101: 38 | K101: The business in the confectionery market is subject to seasonal fluctuations. | L101: ok | M101: demo reviewer | O101: https://vanillabonds.com/dossier-data/pdf/katjes/katjes-2023-annual-report.pdf#page=38
A102: F101 | B102: risk | C102: risk_fact | D102: Risk fact | H102: Key-person dependence on individual managers and skilled personnel stated by management. | I102: S1 | J102: 39 | K102: The success of Katjes International depends on the knowledge and experience of individual managers and skilled personnel. | L102: ok | M102: demo reviewer | O102: https://vanillabonds.com/dossier-data/pdf/katjes/katjes-2023-annual-report.pdf#page=39
A103: F102 | B103: risk | C103: risk_fact | D103: Risk fact | H103: Structural: the holding provides services to subsidiaries for payment but its earnings depend largely on the results of the subsidiaries and holdings. | I103: S1 | J103: 39 | K103: holdings in return for payment, but its earnings are largely depending on the results of the subsidiaries and holdings. | L103: ok | M103: demo reviewer | O103: https://vanillabonds.com/dossier-data/pdf/katjes/katjes-2023-annual-report.pdf#page=39
A104: F103 | B104: risk | C104: risk_fact | D104: Risk fact | H104: Cyberattack risk (hacking, phishing) named as increasing; a single attack could cause business interruption or data loss. | I104: S1 | J104: 39 | K104: The risk of cyberattacks (e.g. hacking attacks, phishing emails) is increasing all the time. | L104: ok | M104: demo reviewer | O104: https://vanillabonds.com/dossier-data/pdf/katjes/katjes-2023-annual-report.pdf#page=39
A105: F104 | B105: risk | C105: risk_fact | D105: Risk fact | H105: Cash and cash equivalents of EUR 2.0m (SEK 24.0m) held in foreign currency at 31 Dec 2023; currency conversion effect EUR 0.0m. | I105: S1 | J105: 48 | K105: As at 31 December 2023, cash and cash equivalents in a foreign currency with a value of EUR 2.0 million (SEK 24.0 million) are reported. | L105: ok | M105: demo reviewer | O105: https://vanillabonds.com/dossier-data/pdf/katjes/katjes-2023-annual-report.pdf#page=48
A106: F105 | B106: risk | C106: risk_fact | D106: Risk fact | H106: Functional currency of Candy Kittens and Longaim is GBP; closing rate GBP 1.15, average 1.15, SEK closing 11.10. | I106: S1 | J106: 53 | K106: The financial statements of Candy Kittens and Longaim, whose functional currency is GBP as opposed to the Euro, | L106: ok | M106: demo reviewer | O106: https://vanillabonds.com/dossier-data/pdf/katjes/katjes-2023-annual-report.pdf#page=53
A107: F106 | B107: risk | C107: risk_fact | D107: Risk fact | H107: Interest-rate sensitivity on factoring (three- and two-month Euribor): a 1% change moves profit after tax by EUR 0.8m in 2023 (2022: EUR 0.2m). | I107: S1 | J107: 61 | K107: len by 1%, profit after tax would have been EUR 0.8 million lower/EUR 0.8 million higher in the reporting year | L107: ok | M107: demo reviewer | O107: https://vanillabonds.com/dossier-data/pdf/katjes/katjes-2023-annual-report.pdf#page=61
A108: F107 | B108: risk | C108: risk_fact | D108: Risk fact | H108: No hedging instruments for currency risk at 31 December 2023; Candy Kittens and Longaim report in GBP; cash of EUR 2.0m held in SEK (SEK 24.0m). | I108: S1 | J108: 61 | K108: As at 31 December 2023, there are no hedging | L108: ok | M108: demo reviewer | O108: https://vanillabonds.com/dossier-data/pdf/katjes/katjes-2023-annual-report.pdf#page=61
... A114: F113 | B114: management | C114: mgmt_person | D114: Executive: name, role, since, prior roles (register / report) | H114: Tobias Bachmüller, Managing Shareholder of Katjes International since 1996; until 1995 General Manager Kraft Foods (Milka), until 1992 Principal at The Boston Consulting Group. | I114: S1 | J114: 6 | K114: since 1996 – Managing Shareholder of Katjes International until 1995 – General Manager, Kraft Foods (Milka) | L114: ok | M114: demo reviewer | O114: https://vanillabonds.com/dossier-data/pdf/katjes/katjes-2023-annual-report.pdf#page=6
A115: F114 | B115: management | C115: revenue_budget | D115: Revenue as budgeted for that year (management plan at the time) | E115: FY2023 | G115: EUR m | H115: Guidance for 2023 as stated: consolidated net sales EUR 350m–375m (raised during the year); actual 377.4 exceeded it | I115: S1 | J115: 41 | K115: The company expected to achieve consolidated net sales of between EUR 350 million and EUR 375 million for the financial year 2023. | L115: ok | M115: demo reviewer | O115: https://vanillabonds.com/dossier-data/pdf/katjes/katjes-2023-annual-report.pdf#page=41
A116: F115 | B116: management | C116: ebitda_budget | D116: EBITDA as budgeted for that year (management plan at the time) | E116: FY2023 | G116: EUR m | H116: Guidance for 2023 as stated: EBITDA margin 9–10%; actual 10.8% | I116: S1 | J116: 41 | K116: Katjes International’s EBITDA margin in the reporting year was 10.8%, well above the forecast range of 9–10%. | L116: ok | M116: demo reviewer | O116: https://vanillabonds.com/dossier-data/pdf/katjes/katjes-2023-annual-report.pdf#page=41
A117: F116 | B117: management | C117: acquisition | D117: Acquisition / disposal: target, year, price, funding, outcome vs case | H117: target: operating business of Paluani S.p.A., Verona (panettone, colomba), via Sperlari; year: 2022 (effective 1 August 2022); price: not stated; outcome vs case: Paluani had been in insolvency proceedings since October 2021, 2021 sales around EUR 40m, PPA effect 14.1 recognised in 2022 income | I117: S1 | J117: 16 | K117: Effective 1 August 2022, Sperlari laid the foundation to further expand its leadership position in the seasonal business: the company acquired the operating business of Paluani S.p.A. | L117: ok | M117: demo reviewer | O117: https://vanillabonds.com/dossier-data/pdf/katjes/katjes-2023-annual-report.pdf#page=16
A118: F117 | B118: management | C118: acquisition | D118: Acquisition / disposal: target, year, price, funding, outcome vs case | H118: target: Paluani background; year: 2021 insolvency; outcome: until insolvency proceedings opened in October 2021 Paluani was Italy's fourth-largest panettone producer with 2021 sales around EUR 40m | I118: S1 | J118: 16 | K118: Until insolvency proceedings were opened in October 2021, Paluani was Italy’s fourth-largest panettone producer, with sales of around EUR 40 million in the year 2021. | L118: ok | M118: demo reviewer | O118: https://vanillabonds.com/dossier-data/pdf/katjes/katjes-2023-annual-report.pdf#page=16
A119: F118 | B119: management | C119: acquisition | D119: Acquisition / disposal: target, year, price, funding, outcome vs case | H119: target: Bübchen (baby and kids body care) from Nestlé/Galderma; year: 2020 (May); price: not stated; brand valued at 22.5 in PPA | I119: S1 | J119: 20 | K119: Following the successful acquisition of Bübchen from Nestlé/Galderma in 2020 | L119: ok | M119: demo reviewer | O119: https://vanillabonds.com/dossier-data/pdf/katjes/katjes-2023-annual-report.pdf#page=20
A120: F119 | B120: management | C120: acquisition | D120: Acquisition / disposal: target, year, price, funding, outcome vs case | H120: target: disposal/contribution of French subsidiary Lutti together with Continental Sweets Belgium into CPK S.A.S.; year: 2018 (end of 2018); outcome: around 23% stake in CPK, equity-accounted at 63.7, share of loss -0.7 in 2023 (2022: -0.1), future payments from the transaction still in other financial assets | I120: S1 | J120: 24 | K120: At the end of 2018, Katjes International contributed its French subsidiary Lutti - already the second-largest sugar confectionery brand in France at the time - into CPK | L120: ok | M120: demo reviewer | O120: https://vanillabonds.com/dossier-data/pdf/katjes/katjes-2023-annual-report.pdf#page=24
...

Sheet Documents
A1: Source | B1: Kind | C1: Period | D1: Date | E1: Origin | F1: Audited | G1: Pages | H1: Link
A2: S1 | B2: annual report | C2: FY2023 | D2: 2024-03-27 | E2: Katjes International GmbH & Co. KG, Emmerich am Rhein (consolidated financial statements and group management report; auditor EY GmbH & Co. KG) | F2: TRUE | G2: 95 | H2: https://vanillabonds.com/dossier-data/pdf/katjes/katjes-2023-annual-report.pdf
A3: S2 | B3: annual report | C3: FY2024 | D3: 2025-04-09 | E3: Katjes International GmbH & Co. KG (audited by EY GmbH & Co. KG) | F3: TRUE | G3: 91 | H3: https://vanillabonds.com/dossier-data/pdf/katjes/katjes-2024-annual-report.pdf
A4: S3 | B4: annual report | C4: FY2025 | D4: 2026-04-02 | E4: Katjes International GmbH & Co. KG, Emmerich am Rhein (management; auditor EY GmbH & Co. KG) | F4: TRUE | G4: 92 | H4: https://vanillabonds.com/dossier-data/pdf/katjes/katjes-2025-annual-report.pdf
A5: S4 | B5: term sheet | C5: 2023-09-21 to 2028-09-21 (bond 2023/2028) | D5: 2023-09-21 | E5: Katjes International GmbH & Co. KG (issuer; author of the sheet not stated) | F5: FALSE | G5: 2 | H5: https://vanillabonds.com/dossier-data/pdf/katjes/katjes-bond-2023-2028-terms.pdf
A6: S5 | B6: interim report | C6: H1-2026 | D6: 2026-09-08 | E6: Katjes International GmbH & Co. KG | F6: FALSE | G6: 52 | H6: https://vanillabonds.com/dossier-data/pdf/katjes/katjes-h1-2026-interim-report.pdf
A7: S6 | B7: web page | D7: 2026-10-20 | E7: GLEIF | F7: FALSE | G7: 0 | H7: https://api.gleif.org/api/v1/lei-records?filter[entity.legalName]=Katjes International
A8: S7 | B8: web page | D8: 2026-10-20 | E8: onvista | F8: FALSE | G8: 0 | H8: https://www.onvista.de/anleihen/KATJES-INT-IHS-23-28-Anleihe-NO0012888769
A9: S8 | B9: web page | D9: 2026-10-20 | E9: EQS-News via Placera | F9: FALSE | G9: 0 | H9: https://www.placera.se/pressmeddelanden/katjes-international-successfully-taps-its-corporate-bond-by-eur-70-million-20250805
A10: S9 | B10: web page | D10: 2026-10-20 | E10: Hogan Lovells | F10: FALSE | G10: 0 | H10: https://www.hlc.com/de/news/hogan-lovells-beraet-katjes-bei-aufstockung-ihrer-nordic-bonds
A11: S10 | B11: web page | D11: 2026-10-20 | E11: yumda (article dated 2026-04-09, reproducing the company release) | F11: FALSE | G11: 0 | H11: https://www.yumda.com/de/news/1188448/katjes-mit-rekord-bei-umsatz-und-ergebnis.html
A12: S11 | B12: web page | D12: 2026-10-20 | E12: yumda | F12: FALSE | G12: 0 | H12: https://www.yumda.com/de/news/1147058/katjes-und-zuckerproduzenten-streiten-vor-gericht-um-schadensersatz.html
A13: S12 | B13: web page | D13: 2026-10-20 | E13: Wikipedia | F13: FALSE | G13: 0 | H13: https://en.wikipedia.org/wiki/Katjes_International
